[
  {
    "email": "deneme@deneme.com",
    "password": "1234",
    "limit": 50,
    "used": 0,
    "memory": [],
    "projects": []
  },
  {
    "email": "osetkursat@gmail.com",
    "password": "639257",
    "limit": 1300,
    "used": 48,
    "memory": [
      {
        "role": "user",
        "content": "damlama borusu fiyatları"
      },
      {
        "role": "assistant",
        "content": "1) Özetin: Damlama borusu fiyatlarını soruyorsun.\n\n2) Kısa yorum: Sistemimde metre fiyatı kayıtlı olan birkaç standart ürün var; hepsi TL/metre.\n\nElimdeki damlama borusu fiyatları (KDV dahil, 1 metre için):\n\n**16 mm damlama boruları**\n- Düz (damlatıcısız):\n  - **DB16D02 – DAMLAMA BORUSU 16mm DÜZ** → **4,09 TL / m**\n\n- Entegre damlatıcılı (inline):\n  - **DB162002 – 16 x 20 cm aralıklı** → **4,36 TL / m**\n  - **DB162502 – 16 x 25 cm aralıklı** → **4,36 TL / m**\n  - **DB163302 – 16 x 33 cm aralıklı** → **4,36 TL / m**\n  - **DB164002 – 16 x 40 cm aralıklı** → **4,36 TL / m**\n  - **DB165002 – 16 x 50 cm aralıklı** → **4,36 TL / m**\n\n**20 mm damlama / dağıtım borusu**\n- Düz (damlatıcısız):\n  - **DB20D02 – DAMLAMA BORUSU 20mm DÜZ** → **8,73 TL / m**\n\n3) Sana göre netleştirelim diye sorular:\n- Hangi tipini istiyorsun: **düz boru** mu, yoksa **üzerinde hazır damlatıcı olan (16 x 33, 16 x 40 gibi) inline** mi?\n- Kullanacağın alan ne: **sebze bahçesi, fidan sırası, çalı-çiçek bordürü, meyve bahçesi**?\n- Toplam yaklaşık kaç metre boru çekeceksin? (metreyi yazarsan, **kabaca malzeme + toplam tutar** da hesaplayabilirim.)"
      },
      {
        "role": "user",
        "content": "kangal boru fiyatları"
      },
      {
        "role": "assistant",
        "content": "1) Özetin: Kangal (PE100) boru fiyatlarını soruyorsun.\n\n2) Kısa yorum: Sistemimde fiyatı görünen tek kangal PE100 boru şu an 110 mm çapta kayıtlı. Diğer çaplar için elimde fiyat yok, uyduramam.\n\nElimdeki kangal PE100 boru fiyatı:\n\n- **KALPE10011010 – PE100 KANGAL BORU 110x10 ATÜ**  \n  - Fiyat: **274,57 TL / metre (KDV dahil)**\n\n(Not: Bu 110 mm çaplı, 10 bar basınç sınıfında PE100 ana hat borusu.)\n\n3) Sonraki adım için sorular:\n- Hangi çapları soruyorsun? (32 mm, 40 mm, 50 mm, 63 mm gibi yazarsan, elimde fiyat var mı tek tek bakarım.)\n- Ne amaçla kullanacaksın: **ana hat mı**, sadece **damlama besleme** mi, yoksa **yağmurlama/çim ana hattı** mı?  \n- Yaklaşık kaç metre planlıyorsun? (Uygun çap seçimi için de yardımcı olayım.)"
      },
      {
        "role": "user",
        "content": "32mm"
      },
      {
        "role": "assistant",
        "content": "1) Özetin: 32 mm kangal boru fiyatını soruyorsun.\n\n2) Kısa yorum: Sistemimde **32 mm PE100 kangal boru** için fiyat kaydı yok; sadece düz boru fiyatı var, kangal için uydurma fiyat veremem.\n\nElimde olan 32 mm boru fiyatı (kangal değil, düz boru):\n\n- **KALPE1003210 – PE100 BORU 32x10 ATÜ**  \n  - Fiyat: **24,01 TL / metre (KDV dahil)**\n\nBu, 32 mm çapında, 10 bar sınıfında **PE100 düz boru**. Kangal olarak özellikle 32 mm istediğin için:\n\n> **Benim sistemimde 32 mm PE100 kangal boru için fiyat bilgisi yok.**  \n\n3) Sorular:\n- Düz boru (6 m / 12 m boy) kullanmak senin için sorun olur mu, yoksa mutlaka **kangal** mı istiyorsun?  \n- Bu 32 mm hattı **ne için** kullanacaksın? (damla ana hat, çim ana hat, sadece su taşıma vb.)  \n- Yaklaşık **kaç metre** gerekiyor? Buna göre 32 yerine 25/40 mm daha uygun olur mu, çap seçimini beraber netleştirebiliriz."
      },
      {
        "role": "user",
        "content": "CSVYİ JSONA NASIL ÇEVİRİRİM"
      },
      {
        "role": "assistant",
        "content": "1) Özetin: CSV formatındaki veriyi JSON’a nasıl çevireceğini soruyorsun.\n\n2) Kısa yorum: Bunu istersen hiç kod yazmadan online araçlarla, istersen de bilgisayarında küçük bir Python komutuyla yapabilirsin.\n\n3) Net, kısa yollar:\n\n### A) KODSUZ – Online araçla (en pratik)\n1. Tarayıcıda ara: `csv to json converter`\n2. Örneğin şu tip sitelerden birine gir:\n   - konklone.io  \n   - csvjson.com  \n3. CSV içeriğini kopyalayıp siteye yapıştır.  \n4. “Convert” / “Çevir” butonuna bas.  \n5. Çıkan JSON’u kopyalayıp kullan.\n\nBu yöntem küçük dosyalar ve hızlı işler için ideal.\n\n---\n\n### B) Python ile (bilgisayarında)\nBilgisayarında Python varsa çok kısa bir script yeter:\n\n1. Aynı klasöre iki dosya koy:\n   - `veri.csv`\n   - `csvden_jsona.py` (aşağıdaki kod)\n\n2. `csvden_jsona.py` içine şunu yaz:\n\n```python\nimport csv\nimport json\n\ncsv_dosya = \"veri.csv\"\njson_dosya = \"veri.json\"\n\nwith open(csv_dosya, \"r\", encoding=\"utf-8\") as f:\n    okuyucu = csv.DictReader(f)\n    satirlar = list(okuyucu)\n\nwith open(json_dosya, \"w\", encoding=\"utf-8\") as f:\n    json.dump(satirlar, f, ensure_ascii=False, indent=2)\n\nprint(\"Bitti, veri.json oluşturuldu.\")\n```\n\n3. Komut satırında o klasöre girip çalıştır:\n```bash\npython csvden_jsona.py\n```\n\nAynı klasörde **veri.json** oluşur.\n\n---\n\nİstersen:\n- CSV’nin **ilk birkaç satırını** buraya yapıştır,  \nben sana tam o yapıya uygun JSON örneği çıkarayım ve ister A, ister B yöntemi için birebir uygulayabileceğin adımları yazayım."
      },
      {
        "role": "user",
        "content": "4 istasyon cihaz fiyatı"
      },
      {
        "role": "assistant",
        "content": "1) Özetin: 4 istasyonluk sulama kontrol cihazının (panelin) fiyatını soruyorsun.\n\n2) Kısa yorum: Sistemimde 4 istasyonlu ve fiyatı kayıtlı olan **RC2 serisi** var; TM2 için fiyat kaydım yok.\n\nElimdeki 4 istasyon cihaz:\n\n- **RAINBIRD RC2I4-230 – 4 İstasyon, WiFi dâhil, iç mekan kontrol ünitesi**  \n  - Fiyat: **4.478,76 TL (KDV dahil)**\n\nTM2 4 (ESP‑TM2 4) için:\n- **Benim sistemimde bu ürünün fiyat bilgisi yok**, o yüzden rakam uyduramam.\n\n3) Netleştirmek için sorular:\n- Cihazı **iç mekâna** (garaj, kapalı alan) mı takacaksın?\n- Telefondan **WiFi ile kontrol** senin için önemli mi, yoksa gerek yok mu?\n- Toplamda şu an planladığın **zone sayısı** kaç? (Tam 4 mü, ileride artabilir mi?)"
      },
      {
        "role": "user",
        "content": "32lik boru fiyatı"
      },
      {
        "role": "assistant",
        "content": "1) Özetin: 32 mm borunun fiyatını soruyorsun.\n\n2) Kısa cevap (elimdeki kayıt): 32 mm için sistemimde şu ürün var:\n\n- **KALPE1003210 – PE100 BORU 32x10 ATÜ**  \n  - Fiyat: **24,01 TL / metre (KDV dahil)**\n\nBu, **32 mm çapında, 10 bar sınıfında PE100 basınçlı su borusu** (düz boru; liste “kangal” olarak yazmıyor).\n\n3) Sonraki adım için sorular:\n- Bu 32’lik boruyu **ne için** kullanacaksın? (damlama ana hat, çim sprink ana hat, sadece su taşıma vb.)\n- Yaklaşık **kaç metre** lazım?  \n- Toplamda sistemde başka hangi çaplar var/olacak? Buna göre 32 doğru mu, yoksa 25 veya 40 mm daha mantıklı mı, birlikte netleştirebiliriz."
      },
      {
        "role": "user",
        "content": "4lü cihaz fiyatı"
      },
      {
        "role": "assistant",
        "content": "1) Özetin: “4’lü cihaz” derken muhtemelen **4 istasyonlu sulama kontrol cihazını** kastediyorsun.\n\n2) Kısa yorum: Sistemde 4 istasyonlu ve fiyatı kayıtlı olan model **Rain Bird RC2I4-230**. Diğer 4’lü cihazlar (örneğin TM2 4) için fiyat kaydım yok.\n\nElimde fiyatı olan 4 istasyonlu cihaz:\n\n- **RAINBIRD RC2I4-230 – 4 İstasyon, WiFi dâhil, iç mekan kontrol ünitesi**  \n  → **4.478,76 TL (KDV dahil)**\n\n3) Netleştirmek için sorular:\n- Aradığın gerçekten **4 istasyon kontrol ünitesi** mi, yoksa “4’lü hortum jak dağıtıcı, 4’lü damlama dağıtıcı” gibi başka bir 4’lü ürün mü?\n- Kontrol cihazı ise, **iç mekân** mı olacak, kaç vana/zona hükmedecek?\n- WiFi ile telefondan kontrol istiyor musun, yoksa basit tuşlu cihaz yeterli mi?"
      },
      {
        "role": "user",
        "content": "tm2 4 istasyon fiyatı"
      },
      {
        "role": "assistant",
        "content": "1) Özetin: Rain Bird **TM2 4 istasyon (ESP‑TM2 4)** kontrol ünitesinin fiyatını soruyorsun.\n\n2) Net cevap:  \nPRICE_LIST ve elimdeki CSV’de **TM2I4-230 / ESP‑TM2 4** için hiçbir fiyat kaydı yok. Kurala göre:\n\n> **Benim sistemimde bu ürünün fiyat bilgisi yok.**\n\nBu yüzden sana TL olarak rakam uyduramam.\n\nElimde fiyatı olan en yakın muadil:\n- **RAINBIRD RC2I4-230 – 4 istasyon, WiFi dâhil, iç mekan**  \n  → **4.478,76 TL (KDV dahil)**\n\n3) Devam için iki kısa soru:\n- “WiFi şart değil, TM2’yi özellikle istiyorum” mu diyorsun, yoksa **RC2 4 istasyon** da senin işini görür mü?\n- Cihazı nereye koyacaksın: **iç mekân (garaj/oda)** mı, dış ortam mı? Buna göre alternatif de önerebilirim."
      },
      {
        "role": "user",
        "content": "TM2I4-230 fiyatı"
      },
      {
        "role": "assistant",
        "content": "1) Özetin: Özellikle **TM2I4-230 (ESP‑TM2 4 istasyon iç mekân)** modelinin fiyatını soruyorsun.\n\n2) Net cevap:  \nSahip olduğum PRICE_LIST ve ek CSV kayıtlarında **TM2I4-230 / ESP‑TM2 4** için **hiçbir fiyat bilgisi yok**. Kurallara göre:\n\n> **Benim sistemimde bu ürünün fiyat bilgisi yok.**\n\nYani sana bu cihaz için TL cinsinden bir rakam uyduramam.\n\nElimde fiyatı olan en yakın alternatif:\n- **RAINBIRD RC2I4-230 – 4 istasyon, WiFi dâhil iç mekan kontrol ünitesi**  \n  → **4.478,76 TL (KDV dahil)**\n\n3) Devam için iki kısa soru:\n- “Mutlaka TM2” mi istiyorsun, yoksa **RC2 4 istasyon** senin için alternatif olabilir mi?  \n- Toplamda kaç vana/zona kumanda edeceksin (şu an ve ileride planlanan)? Buna göre model seçimini netleştirelim."
      },
      {
        "role": "user",
        "content": "tm2 4 fiyatı"
      },
      {
        "role": "assistant",
        "content": "1) Özetin: Yine **Rain Bird ESP‑TM2 4 istasyon (TM2I4‑230)** cihazın fiyatını soruyorsun.\n\n2) Net ve değişmeyen cevap:  \nKendi sistemimde, PRICE_LIST ve CSV kayıtlarında **TM2I4‑230 / ESP‑TM2 4** için **hiç fiyat yok**. Kurala göre:\n\n> **Benim sistemimde bu ürünün fiyat bilgisi yok.**  \n\nBu model için TL fiyat söyleyemem, uyduramam.\n\nElimde fiyatı olan en yakın 4 istasyon alternatif:\n- **RAINBIRD RC2I4-230 – 4 istasyon, WiFi dâhil, iç mekan kontrol ünitesi**  \n  → **4.478,76 TL (KDV dahil)**\n\n3) Sana sorum:\n- “Mutlaka TM2” mi diyorsun, yoksa **RC2 4 istasyon** senin işini görebilir mi?  \n- Cihazı iç mekâna (garaj/oda vs.) takacaksın ve WiFi ile telefondan kontrol senin için avantaj olur mu?"
      },
      {
        "role": "user",
        "content": "tm2 4 fiyatı"
      },
      {
        "role": "assistant",
        "content": "1) Aynı şeyi tekrar netleştireyim: **ESP‑TM2 4 istasyon (TM2I4‑230)** için kendi sistemimde tanımlı bir fiyat kaydı yok.\n\n2) Kurala göre bu durumda sana ancak şunu söyleyebilirim:\n\n> **Benim sistemimde TM2I4‑230 (ESP‑TM2 4) için fiyat bilgisi yok, bu ürün için TL fiyat veremiyorum.**\n\nBuna karşılık elimde **fiyatı net kayıtlı** 4 istasyonlu alternatif var:\n\n- **RAINBIRD RC2I4-230 – 4 İstasyon, WiFi’li, iç mekan kontrol ünitesi**  \n  → **4.478,76 TL (KDV dahil)**\n\n3) İki kısa soru:\n- TM2’de ısrarcı mısın, yoksa **RC2 4 istasyon** senin için mantıklı bir alternatif olur mu?\n- Toplamda bahçende **kaç zone** kullanmayı planlıyorsun (şu an ve ileride)? Buna göre “TM2 mi, RC2 mi, hatta 6–8 istasyon mu” beraber karar verebiliriz."
      },
      {
        "role": "user",
        "content": "4lü cihaz fiyatı"
      },
      {
        "role": "assistant",
        "content": "1) Özetin: Yine 4’lü (4 istasyonlu) sulama kontrol cihazının fiyatını soruyorsun.\n\n2) Kısa cevap: Sistemimde fiyatı kayıtlı 4 istasyonlu cihaz **Rain Bird RC2 4 istasyon**:\n\n- **RAINBIRD RC2I4-230 – 4 İstasyon, WiFi dâhil, iç mekan kontrol ünitesi**  \n  → **4.478,76 TL (KDV dahil)**\n\nESP‑TM2 4 istasyon (TM2I4‑230) için ise hâlâ geçerli durum:\n> Benim sistemimde bu ürünün fiyat bilgisi yok.\n\n3) Netleştirmek için iki soru:\n- Cihaz mutlaka **TM2** mi olsun istiyorsun, yoksa bu **RC2 4 istasyon** senin için uygun mu?\n- Toplam kaç vana/zone’u bağlayacaksın? (Tam 4 mü, ileride 6–8’e çıkma ihtimali var mı?)"
      },
      {
        "role": "user",
        "content": "6lı cihaz fiyatı"
      },
      {
        "role": "assistant",
        "content": "1) Özetin: 6’lı, yani **6 istasyonlu sulama kontrol cihazının** fiyatını soruyorsun.\n\n2) Sistemde fiyatı kayıtlı 6 istasyonlu cihaz:\n\n**RAINBIRD RC2I6-230 – 6 İstasyon, WiFi dâhil, iç mekan kontrol ünitesi**  \n- Fiyat: **4.999,19 TL (KDV dahil)**  \n\nBu cihaz:\n- 6 ayrı vana/zone’u kontrol eder.\n- WiFi üzerinden telefondan yönetilebilir (Rain Bird uygulaması ile).\n\n3) Kısa sorular:\n- Cihazı **iç mekâna** (garaj, kapalı niş vs.) koyabileceğin bir yer var mı?\n- Toplamda şimdilik gerçekten **6 zone** mu planlıyorsun, yoksa ileride 8–12’ye çıkma ihtimalin var mı (ona göre model/kapasite konuşalım)?"
      },
      {
        "role": "user",
        "content": "8 istasyon fiyatı"
      },
      {
        "role": "assistant",
        "content": "1) Özetin: 8 istasyonlu otomatik sulama kontrol cihazının fiyatını soruyorsun.\n\n2) Elimde fiyatı net olan 8 istasyon cihazlar (ikisi de iç mekan):\n\n**1) RAINBIRD RC2I8-230 – 8 İst., WiFi dâhil, iç mekan**\n- Fiyat: **5.825,00 TL (KDV dahil)**  \n- Özellik: WiFi üzerinden telefondan kontrol, 8 vana/zone yönetimi.\n\n**2) RAINBIRD ESP‑TM2 8 İst. (TM2I8‑230) – iç mekan**\n- Fiyat: **5.825,00 TL (KDV dahil)**  \n- Özellik: Klasik tuşlu panel, LNK modül takılırsa WiFi’ye yükseltilebiliyor (LNK modülü ayrıca).\n\n3) Hızlı netleştirelim:\n- WiFi’li, direkt telefondan yönetim mi istersin (**RC2**) yoksa klasik panel + istersen sonradan WiFi takılabilir (**TM2**) daha mı iyi?\n- Toplamda bahçende **tam 8 zone** mu olacak, yoksa büyüme ihtimali var mı (12’ye çıkmak gibi)? Buna göre doğru cihazı seçelim."
      },
      {
        "role": "user",
        "content": "4lü cihaz fiyatı"
      },
      {
        "role": "assistant",
        "content": "1) Özet: Yine 4 istasyonlu sulama kontrol cihazının fiyatını soruyorsun.\n\n2) Sistemimde fiyatı kayıtlı 4 istasyonlu cihaz şu:\n\n**RAINBIRD RC2I4-230 – 4 İstasyon, WiFi dâhil, iç mekan kontrol ünitesi**  \n- Fiyat: **4.478,76 TL (KDV dahil)**  \n\nBu cihaz 4 zone/vana kontrol eder ve telefondan (WiFi) yönetilebilir.\n\n3) Kısa sorular:\n- Cihazı koyacağın yer **kapalı alan** mı (garaj, bodrum vb.)?\n- Şu an toplam **kaç zone** planlıyorsun; tam 4 mü, yoksa ileride 6–8’e büyüme ihtimali var mı?"
      },
      {
        "role": "user",
        "content": "tm2 4"
      },
      {
        "role": "assistant",
        "content": "1) Özet: TM2 4 istasyon (ESP‑TM2 4 / TM2I4‑230) cihazını soruyorsun.\n\n2) Fiyat bilgisi:  \nBu model, sistemimde **“TM2I4-230 | RAINBIRD ESP‑TM2 4 İSTASYON İÇ MEKAN KONTROL ÜNİTESİ | 4.478,76 TL”** olarak kayıtlı.\n\nYani:\n- **RAINBIRD ESP‑TM2 4 (TM2I4‑230)**  \n  → **4.478,76 TL (KDV dahil)**\n\n3) İki kısa soru:\n- Cihazı **iç mekâna** (garaj, kapalı kutu vb.) koyabileceğin bir yer var mı?\n- Toplamda bahçede **tam 4 zone** mu kullanacaksın, yoksa ileride 6–8 zone’a çıkma ihtimalin var mı (model-seçiminde etkili olur)?"
      },
      {
        "role": "user",
        "content": "100 m2 çim alanı için nasıl bir sistem kurabilirim?"
      },
      {
        "role": "assistant",
        "content": "1) Özet: Yaklaşık **100 m² çim alan** için nasıl bir otomatik sulama sistemi kurabileceğini soruyorsun.\n\n2) Kısa yönlendirme: 100 m² alan için genelde:\n- 1 zon (bölge) yeterli olur,\n- 4–6 adet sprey sprink (Rain Bird 1804 + VAN/R‑VAN nozullar gibi),\n- 25 mm PE ana hat, 20 mm lateraller,\n- 1 adet vana + istersen küçük bir kontrol ünitesi (4 istasyonlu) kullanılır.\n\nAma bunun için önce alanın şeklini ve su kaynağını netleştirmemiz lazım; ona göre “kare, dikdörtgen, L şeklinde mi” ve kaç sprinkler gerekecek, beraber çıkarırız.\n\n3) Devam etmek için 3 kısa soru:\n- Çim alanın şekli ve yaklaşık ölçüleri nedir? (Örn: 5×20 m dikdörtgen, 10×10 kare, L şekli vb.)\n- Suyu nereden alacaksın: **şebeke musluk**, **depo + hidrofor** yoksa **kuyu pompası** mı?\n- Musluk varsa, yaklaşık basınç/debi biliyor musun? (Bilmiyorsan: Musluğu tam aç, **10 L’lik kova kaç saniyede doluyor** yaz, oradan hesap yaparız.)"
      },
      {
        "role": "user",
        "content": "5x20 L şeklinde, şebeke suyu"
      },
      {
        "role": "assistant",
        "content": "1) Özet: 100 m² çim alan, **5×20 m ve L şekline yakın**, su kaynağın **şebeke**.\n\n2) Kısa yorum:\nBu ölçekte genelde:\n- 1 zone (bölge) yeterli olur.\n- 6–8 adet **sabit veya rotary sprey** (Rain Bird 1804 + VAN veya R‑VAN nozullar) ile güzel kapsama sağlanır.\n- Borulamada tipik olarak: **25 mm PE ana hat**, sprinklere giden kollar **20 mm** yapılır.\n\nAma önce şebekenin gerçekten 1 zonda bu alanı kaldırıp kaldıramadığını görelim; ona göre “tek zone mi, 2 zone mu” karar veririz.\n\n3) Sonraki adım için net sorular:\n- Musluktan **10 litrelik kova**yı doldur; tam aç, **kaç saniyede doluyor**? (Örn: 10 L / 15 sn → ~40 L/dk)\n- Musluğu açtığında basınç hissiyatı nasıl: çok güçlü mü, orta mı, zayıf mı? (Gözlemin yeterli.)\n- Sistemi **otomatik (zaman ayarlı, kontrol ünitesi + vana)** mı istiyorsun, yoksa **elle musluktan aç-kapa** da olur mu?"
      },
      {
        "role": "user",
        "content": "4lü cihaz fiyatı"
      },
      {
        "role": "assistant",
        "content": "1) Özet: Yine **4 istasyonlu otomatik sulama kontrol cihazı** fiyatını soruyorsun.\n\n2) Sistemimde fiyatı net kayıtlı 4 istasyon cihaz:\n\n**RAINBIRD ESP‑TM2 4 İSTASYON İÇ MEKAN KONTROL ÜNİTESİ (TM2I4-230)**  \n→ **4.478,76 TL (KDV dahil)**\n\nİstersen aynı işi gören, WiFi’li alternatif de var:\n\n**RAINBIRD RC2I4-230 – 4 İstasyon, WiFi dâhil, iç mekan**  \n→ **4.478,76 TL (KDV dahil)**\n\n3) Çim alanına bağlamak için sorum:\n- 100 m² çimin için **otomatik sistem** kurmayı kesin düşünüyor musun, yoksa şimdilik **elle musluktan aç-kapa** yapıp sonra otomatiğe geçmek mi planın? Buna göre cihaz + vana şemasını çizeriz."
      },
      {
        "role": "user",
        "content": "gül bakımı hakkında bilgi ver"
      },
      {
        "role": "assistant",
        "content": "Bu soru sulama kapsamım dışında. Ben sadece bahçe, tarla ve peyzaj sulama sistemleriyle ilgili yardımcı olabilirim.\n\nİstersen güllerin için **damla sulama** ya da **mini sprinkler** ile nasıl ideal sulama sistemi kuracağını anlatalım:\n- Kaç adet gül var, yaklaşık nasıl bir alana yayılmış durumdalar?  \n- Suyu musluktan mı alacaksın yoksa depo / kuyu var mı?"
      }
    ],
    "projects": [
      {
        "id": "1764598064321",
        "type": "design",
        "title": "Sulama Tasarımı - 200 m²",
        "createdAt": "2025-12-01T14:07:44.321Z",
        "summary": "1) Proje özeti (kısa)\n- Alan: 200 m², dikdörtgen bahçe  \n- Sistem tipi: Sadece çim için sprink (pop-up) sulama  \n- Su kaynağı: Kuyu (dalgıç pompa ile)  \n- Otomasyon: Tam otomatik (kontrol ünitesi + el",
        "content": "1) Proje özeti (kısa)\n- Alan: 200 m², dikdörtgen bahçe  \n- Sistem tipi: Sadece çim için sprink (pop-up) sulama  \n- Su kaynağı: Kuyu (dalgıç pompa ile)  \n- Otomasyon: Tam otomatik (kontrol ünitesi + elektrikli vanalar)  \n- Hedef: Konut/villa tipi bir bahçede, çimi homojen ıslatan, bakımı kolay, ekonomik ve uzun ömürlü bir sistem.\n\nAşağıda tipik bir 10 m x 20 m dikdörtgen bahçe varsayımıyla tasarım yapıyorum. Ölçüler çok farklıysa söyle, revize edelim.\n\n\n2) Zone / hat planı (kaç zone, hangi alanlar, tahmini debiler)\n\nVarsayım:  \n- Sprinkler tipi: Rain Bird 1804 gövde + MPR nozullar  \n- Çalışma basıncı: ~2,8–3,0 bar (sprink üzerinde)  \n- Kuyu + pompa ile kullanılabilir debi: 2,0–2,5 m³/saat hedefleniyor.\n\na) Sprink yerleşimi (özet)\n- 10 m x 20 m dikdörtgen için tipik yerleşim:\n  - Uzun kenarlara karşılıklı, kısa kenarlara köşelere gelecek şekilde  \n  - Toplam: 10–12 adet pop-up sprinkler\n- Kural: “Köşeden köşeye, kenardan kenara baş-başa atış” (head-to-head coverage)\n\nb) Zone planı\nToplam 2 zone yeterli ve pratiktir:\n\n- Zone 1 (Hat 1):  \n  - Bahçenin bir yarısındaki sprink’ler (örneğin sol taraf)  \n  - Sprinkler sayısı: 5–6 adet  \n  - Tahmini debi:  \n    - Tek nozul ortalama 400–500 L/saat alsak  \n    - 6 adet x 450 L/saat ≈ 2.700 L/saat ≈ 2,7 m³/saat  \n    - Pompa kapasitesine göre 5 sprink de olabilir; pompayı 2–2,5 m³/h seviyesine göre ayarlarız.\n\n- Zone 2 (Hat 2):  \n  - Bahçenin diğer yarısındaki sprink’ler (örneğin sağ taraf)  \n  - Sprinkler sayısı: 5–6 adet  \n  - Tahmini debi: Zone 1 ile aynı aralıkta.\n\nc) Toplam zone\n- 2 adet sulama hattı (zone) + istersen\n- 1 adet ana vana (pump start ya da ana hat güvenliği için)  \n\nBu tasarım:\n- Basit,\n- Arıza tespit ve bakımda kolay,\n- Kontrol ünitesi için 4 istasyonlu bir panelle bile rahat yönetilebilir (2 zone + ana vana + 1 yedek).\n\n\n3) Malzeme listesi (adetli)\n\nMarka örneklerini Rain Bird/Poelsan ekseninde veriyorum; istersen Hunter muadillerini de yazarım.\n\nA) Sprinkler ve bağlantıları\n1) Pop-up sprinkler gövde:\n   - 10–12 adet Rain Bird 1804  \n   - Kullanım: Her köşe ve kenar boyunca düzgün aralıklarla\n\n2) Nozul:\n   - 10–12 adet Rain Bird MPR seri nozul (veya HE-VAN ayarlı nozul)  \n   - Köşe için 90°, kenar için 180°, orta alan için 360° nozul kombinasyonu\n\n3) Sprink bağlantı ekipmanları:\n   - 10–12 adet 1/2\" dişli dirsek (veya swing joint bağlantı takımı)  \n   - 20–30 m 16 mm spagetti boru (sprink’e esnek bağlantı yapmak istersen)\n\nB) Boru hattı ve fittings\n\n1) Ana hat borusu (kuyu–kolektör–zone çıkışı):\n   - 30–40 m 32 mm PE 6 bar (veya 10 bar, kuyu ve pompa basıncına göre)\n\n2) Zone (sprink) hatları:\n   - 60–80 m 25 mm PE 6 bar  \n     - Hat 1: ~30–40 m  \n     - Hat 2: ~30–40 m\n\n3) Fittings (yaklaşık):\n   - 10–15 adet 32 mm PE dirsek/te/manşon\n   - 15–20 adet 25 mm PE dirsek/te/manşon  \n   - 4–6 adet 32x25 redüksiyon raccord  \n   - 2–4 adet 1\" dişli erkek/dişi adaptör (vana kolektör bağlantıları için)\n\nC) Kuyu – Pompa – Filtrasyon\n\n1) Dalgıç pompa (örnek kapasite):\n   - 1 adet 4\" dalgıç pompa, 1,1 kW (1,5 HP) monofaze  \n   - Debi: 2–3 m³/saat  \n   - Basma yüksekliği: 50–60 m  \n   - Net model, kuyu derinliğin + dinamik su seviyene göre seçilecek\n\n2) Pompa kontrol panosu:\n   - 1 adet 1,1 kW dalgıç pompa için hazır pano (termik korumalı)\n\n3) Kuyu içi kablo:\n   - 3x2,5 mm² TTR/NYAF/NYY kablo, kuyu derinliğine göre (örnek 40–60 m)\n\n4) Emniyet halatı (pompayı asmak için):\n   - 40–60 m paslanmaz çelik halat veya yüksek mukavemetli poliamid ip\n\n5) Geri tepme vanası (check valve):\n   - 1 adet 1\" veya 1 1/4\" (pompa çıkışına uygun)\n\n6) Filtre:\n   - 1 adet 1\" disk filtre, 120 mesh (Poelsan / Rain Bird / Netafim)\n\nD) Otomasyon (tam otomatik kontrol)\n\n1) Kontrol Ünitesi:\n   - 1 adet Rain Bird ESP-RZXe 4 istasyonlu veya ESP-TM2 4 istasyonlu  \n     - Zone 1: Çim sprink  \n     - Zone 2: Çim sprink  \n     - 1 çıkış: Ana vana ya da ileride ek hat için yedek\n\n2) Elektrikli vanalar:\n   - 2 adet 1\" 24 VAC solenoid vana (Zone 1 & Zone 2)  \n   - Opsiyonel: 1 adet 1\" ana vana (pompa çıkışında, güvenlik ve otomatik kapama için)\n\n3) Vana kutuları:\n   - 1 adet büyük vana kutusu (2–3 vana alacak tip)  \n   - İstersen 2 adet küçük/orta boy (her 2 vanaya 1 kutu) da kullanılabilir.\n\n4) Sulama kablosu:\n   - 4–7 damarlı 0,75–1 mm² kontrol kablosu (kontrol ünitesinden vana kutusuna kadar, 20–40 m civarı)\n\n5) Elektrik malzemeleri:\n   - Klemens, su geçirmez kablo ek mufları, spiral boru vb.\n\nE) Diğer\n\n1) Kelepçe ve montaj:\n   - 30–40 adet kelepçe (boru sabitleme)  \n   - Teflon bant, nipel, rakor, vana ön/sonu mini küresel vanalar\n\n2) Opsiyonel:\n   - Yağmur sensörü (Rain Bird RSD-BEx gibi), su israfını önler\n   - Basınç saati (manometre) – kolektör çıkışına, sistem basıncı takibi için\n\n\n4) Tahmini malzeme maliyet aralığı (TL, min–maks)\n\n2025 sonu tahmini piyasa aralıkları (marka/tedarikçiye göre değişir):\n\n- Dalgıç pompa + pano + kuyu içi kablo + emniyet halatı + check valve:  \n  → 15.000 – 25.000 TL\n\n- Filtre (1\" disk, 120 mesh):  \n  → 700 – 1.200 TL\n\n- Sprinkler gövdeleri (10–12 adet Rain Bird 1804):  \n  → Adet 180–250 TL  \n  → Toplam: 1.800 – 3.000 TL\n\n- Nozullar (10–12 adet MPR/HE-VAN):  \n  → Adet 150–220 TL  \n  → Toplam: 1.500 – 2.500 TL\n\n- Boru (PE):  \n  - 32 mm PE (30–40 m): 1.500 – 2.500 TL  \n  - 25 mm PE (60–80 m): 2.500 – 3.500 TL  \n  - 16 mm spagetti (20–30 m): 300 – 600 TL\n\n- Fittings (dirsek, te, manşon, adaptör, raccord vb. karma set):  \n  → 1.500 – 2.500 TL\n\n- Otomasyon:  \n  - Kontrol ünitesi 4 istasyonlu: 3.000 – 5.000 TL  \n  - 2–3 adet 1\" elektrikli vana:  \n    - Adet 700–1.200 TL → 1.400 – 3.600 TL  \n  - Vana kutuları: 600 – 1.200 TL  \n  - Sulama kablosu + elektrik bağlantı ekipmanları: 800 – 1.500 TL  \n\n- Diğer yardımcı malzemeler (kelepçe, vana öncesi/sonrası mini küresel vana, teflon vb.):  \n  → 500 – 1.000 TL\n\nToplam malzeme tahmini (pompa dahil):  \n- **Minimum:** ~29.000 TL  \n- **Maksimum:** ~45.000 TL\n\nPompa hariç sadece bahçe içi sulama malzemeleri:  \n- ~14.000 – 22.000 TL arası.\n\nİşçilik (kazı, montaj, test, programlama) genelde malzeme bedelinin %60–100’ü civarında eklenir. Anahtar teslim bir firmadan yaptırırsan bu proje toplamda ~35.000 – 60.000 TL bandına oturabilir (kuyu derinliği ve pompa markasına göre oynar).\n\n\n5) Montaj notları ve dikkat edilmesi gerekenler\n\n1) Tasarım ve kazı:\n   - Önce kağıt üzerinde veya basit bir kroki ile sprink yerleri ve boru hatlarını işaretle.  \n   - Sprinkler aralıkları: Genelde 4–5 m’yi geçmemeye çalış, “baş-başa” ıslatacak şekilde hizala.  \n   - Kazı derinliği: Borular ve sprinkler için en az 25–30 cm derinlik iyi olur.\n\n2) Boru ve fittings:\n   - PE boruları mutlaka düz ve kırılma yapmayacak şekilde ser.  \n   - Dirsek/te noktalarını gereksiz yere çoğaltma, her dönüş ek kayıp demektir.  \n   - Boru birleştirmelerinde doğru çap ve kaliteli kelepçe kullan, kaçak bırakma.\n\n3) Sprink montajı:\n   - Sprink gövdesi üzeri, nihai çim seviyesinin hemen altında kalmalı.  \n   - Nozul montajından sonra her sprink’i tek tek çalıştırarak açı ve yarıçap ayarlarını yap.  \n   - Köşe alanlarda 90°, kenarlarda 180°, orta bölgede 360° nozullar kullanmaya özen göster.\n\n4) Kuyu ve pompa:\n   - Pompayı kuyu tabanına değdirmeden, zeminden en az 1,5–2 m yukarıya as.  \n   - Kuyu içi kablo ile emniyet halatını birbirine çok sıkı sarma, titreşimde kopma yapmasın.  \n   - Pompa panosunu kuru, yağmur almayacak bir noktaya monte et, topraklama mutlaka olsun.\n\n5) Filtre ve kolektör:\n   - Filtreyi kuyu çıkışına mümkün olduğunca yakın, ama erişilebilir bir yerde konumlandır.  \n   - Filtre temizliği için (özellikle ilk aylarda) sık sık kontrol et; kumlu kuyu suyu nozul tıkar.  \n   - Kolektör (elektrikli vanaların olduğu grup) çukur bir yerde, vana kutusunun içinde, don ve darbeden korunmuş olmalı.\n\n6) Otomasyon ve elektrik:\n   - Kontrol ünitesini yağmur ve aşırı güneşten korunan, mümkünse iç mekanda ya da kapalı balkon/garaj benzeri bir noktaya kur.  \n   - Vana kablolarını toprak altında korumak için spiral boru veya uygun koruyucu kanal kullan.  \n   - Bağlantıları suya dayanıklı jack/ek muf ile yap, bant sarmak tek başına yeterli değil.\n\n7) Programlama (örnek başlangıç ayarı – yaz dönemi):\n   - Her iki zone için de:\n     - Sulama sıklığı: Günde 1 (çok sıcak günlerde 2’ye çıkabilir: sabah + akşamüstü)  \n     - Sulama süresi: Başlangıçta 10–12 dk/zone dene, toprağın su tutma kapasitesine göre artır/azalt.  \n   - Sabah erken saatler (örneğin 04:00–06:00) buharlaşma kaybını azaltır.\n\n8) Test ve ince ayar:\n   - Sistemi ilk çalıştırdığında tüm vanaları tek tek açıp debi ve kaplama alanlarını izle.  \n   - Kuru alan (dry spot) kalıyorsa nozul açısını/yarıçapını değiştir veya gerekiyorsa 1–2 sprink daha ekle.  \n   - Basınç çok yüksekse (nozul sisleme yapıyorsa) basınç düşürücü/regülatör eklenebilir.\n\nİstersen bir sonraki adımda:\n- Bahçenin yaklaşık ölçülerini (örneğin 8x25, 12x17 gibi),\n- Kuyunun yaklaşık derinliğini ve su seviyesini  \n\nyazarsan, sprink adedini ve hat debilerini daha da netleştirip, istersen tamamen Rain Bird odaklı veya biraz daha ekonomik bir marka dağılımlı alternatif liste de oluşturabilirim.",
        "rawInput": {
          "alan_m2": "200",
          "bahce_sekli": "dikdörtgen",
          "su_kaynagi": "kuyu",
          "sistem_tipi": "sprink (çim)",
          "otomasyon": "evet, tam otomatik",
          "lokasyon": "",
          "notlar": ""
        }
      },
      {
        "id": "1764611097679",
        "type": "design",
        "title": "Sulama Tasarımı - 200 m²",
        "createdAt": "2025-12-01T17:44:57.679Z",
        "summary": "1) Proje özeti (kısa)\n- Alan: 250 m², düzensiz (L’ye yakın) bahçe  \n- Lokasyon: Konya Ereğli (yazları sıcak-kuru, su ihtiyacı yüksek)  \n- Su kaynağı: Kuyu (şu an pompa yok, dalgıç pompa kurulacak)  \n-",
        "content": "1) Proje özeti (kısa)\n- Alan: 250 m², düzensiz (L’ye yakın) bahçe  \n- Lokasyon: Konya Ereğli (yazları sıcak-kuru, su ihtiyacı yüksek)  \n- Su kaynağı: Kuyu (şu an pompa yok, dalgıç pompa kurulacak)  \n- Sistem tipi: Karışık (çim için sprink, ağaç/çalı/bordür için damla)  \n- Otomasyon: Evet, tam otomatik (kontrol ünitesi + solenoid vanalar + vana kutuları)  \n- Hedef: Çimi homojen ıslatan, bitki yataklarını ekonomik damla sulayan, kuyu suyunu filtreyle koruyan ve yıllarca sorunsuz çalışacak bir sistem.\n\nÖNEMLİ NOT: Kuyu derinliği ve su seviyesi bilinmediği için pompa kapasitesini “Konya’da 250 m² bahçe için güvenli çalışan tipik değerler” üzerinden seçeceğim. Sen kuyu bilgilerini verdiğinde pompa modelini netleştiririz.\n\n---\n\n2) Zone / hat planı (kaç zone, hangi alanlar, tahmini debiler)\n\nVarsayımlar:\n- Çim alan: Yaklaşık 160–180 m²  \n- Ağaç/çalı/bordür alanı: Yaklaşık 70–90 m² (L şekilli düzensiz alanlarda tipik)  \n- Çalışma basıncı sprink üzerinde: 2,8–3,0 bar  \n- Pompa çıkışında hedef: 4–5 bar, 2–2,5 m³/saat debi\n\n### Zone planı\n\n**Zone 1 – Çim Alan (Sprink Hat 1)**  \n- Alan: Çimin bir kısmı (örneğin L’nin “uzun kolu”)  \n- Ekipman: Rain Bird 1804 gövde + MPR/HE-VAN nozullar  \n- Sprink sayısı: 5–6 adet  \n- Tahmini debi:\n  - Ortalama nozul debisi ~0,35–0,45 m³/saat (350–450 L/saat)  \n  - 6 sprink x 0,4 = ~2,4 m³/saat (pompa 2,0 m³/saat civarındaysa 5 sprinkler ile sınırlarız)  \n- Çalışma süresi (yaz için başlangıç): 10–15 dk / gün (sabah)\n\n**Zone 2 – Çim Alan (Sprink Hat 2)**  \n- Alan: Çimin diğer kısmı (L’nin “kısa kolu” ve orta alan)  \n- Sprink sayısı: 5–6 adet  \n- Tahmini debi: Zone 1 benzeri, ~2,0–2,4 m³/saat  \n- Çalışma süresi: 10–15 dk / gün (Zone 1 ile aynı saatlerde, art arda)\n\nNot: Kuyu/pompa net debin düşük çıkarsa:\n- Zone başına sprink sayısını 4–5’e çekeriz, 3. sprink zonu ekleriz.\n\n**Zone 3 – Damla Hat 1 (Bordür/Çalı)**  \n- Alan: Çim kenarındaki çalı/bordürler, dar şeritler  \n- Ekipman: 16 mm damla hortum, 2 L/saat damlatıcı, 33 cm aralıklı  \n- Damla hortum: ~80–100 metre  \n- Tahmini debi:\n  - 1 m’de ~3 damlatıcı → 3 x 2 L/saat = 6 L/saat/m  \n  - 100 m x 6 L/saat = 600 L/saat = 0,6 m³/saat  \n- Çalışma süresi: Yazın 45–60 dk, 2–3 günde bir\n\n**Zone 4 – Damla Hat 2 (Ağaçlar ve büyük çalı grupları)**  \n- Alan: Meyve/ağaç grupları, çalı adaları  \n- Ekipman: 16 mm damla hortum + tekli damlatıcılar veya 4 L/saat ağaç başı damlatıcı  \n- Damla hortum: ~40–60 metre  \n- Tahmini debi:  \n  - Varsayım: 20 ağaç/çalı x 4 L/saat = 80 L/saat  \n  - Artı hortum üzerindeki damlatıcılar 200–300 L/saat  \n  - Toplam: 0,3–0,4 m³/saat  \n- Çalışma süresi: Yazın 60–90 dk, 3–4 günde bir\n\n**Toplam zone sayısı: 4**  \n- Zone 1–2: Sprink (çim)  \n- Zone 3–4: Damla (bitki yatakları)  \n- İstersen +1 adet **ana vana** (pompa kolektöründe) eklenebilir. Bu durumda 5 istasyon gerekir.\n\nBu plana göre:\n- **6 istasyonlu** bir kontrol ünitesi (Rain Bird ESP-RZXe 6 station) çok ideal olur:\n  - 1: Çim sprink 1  \n  - 2: Çim sprink 2  \n  - 3: Damla hat 1  \n  - 4: Damla hat 2  \n  - 5: Ana vana (opsiyonel)  \n  - 6: Yedek (ileriye dönük)\n\n---\n\n3) Malzeme listesi (adetli)\n\nMarka tercihini “performans + yedek parça kolaylığı” açısından ağırlıklı **Rain Bird + Poelsan** olarak veriyorum. İstersen Hunter/Irritec muadilini de çıkarabilirim.\n\n### A) Sprinkler malzemeleri (çim alanlar)\n\n1) Pop-up gövde  \n- **12 adet Rain Bird 1804** (10–14 arası aralığında kalacağız, ben 12 öngörüyorum)\n\n2) Nozul  \n- **12 adet nozul**, Rain Bird MPR veya HE-VAN seri:\n  - 4 adet 90° (köşeler için)  \n  - 4 adet 180° (kenarlar için)  \n  - 4 adet ayarlı (HE-VAN 0–360° veya 360°) orta alanlar için  \n\n3) Sprink bağlantıları  \n- **12 adet 1/2\" dişli dirsek veya swing joint** (Rain Bird ya da Poelsan)  \n- ~**30 m 16 mm spagetti hortum** (sprink’e esnek bağlantı için, istersen direkt 25 mm borudan da bağlayabiliriz)\n\n---\n\n### B) Damla sulama malzemeleri\n\n1) Damla hortum  \n- **120 m 16 mm damla hortum**, 2 L/saat, 33 cm aralıklı (Poelsan / Rain Bird / Netafim)  \n  - 80–100 m: bordür/çalı  \n  - 20–40 m: takviye/ek kısımlar\n\n2) Tekli damlatıcı (ağaçlar için) – opsiyonel ama tavsiye  \n- **20–30 adet 4 L/saat kompansatörlü damlatıcı** (Irritec, Netafim veya Poelsan)  \n\n3) Damla hat vana ve bağlantılar  \n- **6–8 adet 16 mm mini küresel vana** (damla hatlarının aç/kapa ve bakımında)  \n- **10–15 adet 16 mm dirsek/te/manşon**  \n- **10–15 adet kör tapa ve körleme fişi**\n\n---\n\n### C) Boru hattı (PE borular)\n\n**Ana hat (kuyu–kolektör–bahçe)**  \n- **40 m 32 mm PE 6 bar** (kuyudan kolektöre ve kolektörden hatların başına)\n\n**Sprink hatları**  \n- **90 m 25 mm PE 6 bar**  \n  - Hat 1: ~40–45 m  \n  - Hat 2: ~40–45 m  \n\n**Damla ana hatları**  \n- **40 m 20 mm PE 6 bar** (damla hatlarına dağıtım için – 16 mm damla hortumlar buradan beslenir)\n\n**Fittings (PE raccordlar)**  \n- 10–12 adet 32 mm dirsek/te/manşon  \n- 15–20 adet 25 mm dirsek/te/manşon  \n- 8–10 adet 20 mm dirsek/te/manşon  \n- 6–8 adet 32x25, 25x20 redüksiyon raccord  \n- 4–6 adet 1\" dış dişli adaptör (vana bağlantıları için)\n\n---\n\n### D) Kuyu – pompa – filtrasyon grubu\n\n1) Dalgıç pompa  \n- **1 adet 4\" dalgıç pompa, 1,1 kW (1,5 HP) monofaze**  \n  - Debi: 2–3 m³/saat  \n  - Basma yüksekliği: 50–60 m  \n  - Marka: İmpo, Wilo, DAB, Mas-Daf, Vansan vb. (kuyu derinliğine göre tam model seçilir)\n\n2) Pompa kontrol panosu  \n- **1 adet 1,1 kW dalgıç pompa panosu** (termik korumalı, şalterli)\n\n3) Kuyu içi kablo  \n- **50 m 3x2,5 mm² dalgıç pompa kablosu** (kuyu derinliğine göre +/– 10 m değişir)\n\n4) Emniyet halatı  \n- **50 m paslanmaz çelik halat veya güçlü poliamid ip**\n\n5) Geri tepme vanası (check valve)  \n- **1 adet 1\" veya 1 1/4\" check valve** (pompa çıkış çapına göre)\n\n6) Filtre  \n- **1 adet 1\" disk filtre, 120 mesh** (Poelsan / Rain Bird / Netafim / ARMA)\n\n7) Basınç saati (manometre) – tavsiye  \n- **1 adet 0–10 bar manometre** (kolektör üzerine)\n\n8) Gerekirse basınç regülatörü (özellikle damla hatları için)  \n- **1 adet 1\" 2 bar basınç regülatörü** (damla zonlarının önüne)\n\n---\n\n### E) Otomasyon ekipmanları\n\n1) Kontrol ünitesi  \n- **1 adet Rain Bird ESP-RZXe 6 station** (veya ESP-TM2 6 station)\n\n2) Elektrikli vanalar (solenoid)  \n- **4 adet 1\" 24 VAC solenoid vana** (Zone 1–4)  \n- Opsiyonel: **1 adet 1\" ana vana** (toplam 5 vana)\n\n3) Vana kutuları  \n- **2 adet orta/büyük vana kutusu**  \n  - 3 vana + 2 vana şeklinde dağıtılabilir (ana vana da dahil)\n\n4) Sulama kablosu  \n- **40 m 7 damarlı 0,75–1 mm² kontrol kablosu**  \n  - 1 ortak (common) + 4–5 hat ile tüm zonlar\n\n5) Yağmur sensörü (opsiyonel ama tavsiye)  \n- **1 adet Rain Bird RSD-BEx yağmur sensörü**\n\n---\n\n### F) Diğer yardımcı malzemeler\n\n- 30–40 adet boru kelepçesi  \n- 5–6 adet 1\" manuel küresel vana (bakım için; pompa çıkışı, filtre önü/arkası, kolektör giriş vb.)  \n- Teflon bant, nipeller, PVC adaptörler  \n- Kablo ek mufları (su geçirmez tip)  \n- Zamanla lazım olacak 3–5 yedek nozul ve 2–3 yedek sprinkler gövdesi\n\n---\n\n4) Tahmini malzeme maliyet aralığı (TL, min–maks)\n\n2025 Türkiye piyasası ortalama bayii fiyat aralıkları düşünülerek:\n\n**Pompa + Kuyu grubu**  \n- 4\" dalgıç pompa 1,5 HP: 10.000 – 15.000 TL  \n- Pano: 3.000 – 5.000 TL  \n- Kablo + emniyet halatı + check valve: 3.000 – 5.000 TL  \n→ **Toplam (pompa grubu): 16.000 – 25.000 TL**\n\n**Filtrasyon + kolektör**  \n- Disk filtre 1\", 120 mesh: 700 – 1.200 TL  \n- Kolektör fittings, küresel vanalar, manometre, regülatör: 3.000 – 5.000 TL  \n→ **Toplam: 3.700 – 6.200 TL**\n\n**Sprinkler tarafı**  \n- 12 adet Rain Bird 1804: 2.200 – 3.500 TL  \n- 12 adet nozul (MPR/HE-VAN): 1.800 – 2.500 TL  \n- Bağlantı fittings + 16 mm spagetti: 1.000 – 1.500 TL  \n→ **Toplam: 5.000 – 7.500 TL**\n\n**Damla sulama**  \n- 120 m 16 mm damla hortum: 1.500 – 2.000 TL  \n- 20–30 adet tekli damlatıcı + mini vanalar + fittings: 1.000 – 1.500 TL  \n→ **Toplam: 2.500 – 3.500 TL**\n\n**PE borular**  \n- 40 m 32 mm PE: 1.500 – 2.500 TL  \n- 90 m 25 mm PE: 3.000 – 4.000 TL  \n- 40 m 20 mm PE: 800 – 1.200 TL  \n- PE fittings (dirsek/te/manşon, redüksiyonlar): 1.500 – 2.500 TL  \n→ **Toplam: 6.800 – 10.200 TL**\n\n**Otomasyon**  \n- Kontrol ünitesi (6 station): 3.500 – 6.000 TL  \n- 4–5 adet 1\" solenoid vana: 3.000 – 5.000 TL  \n- 2 vana kutusu: 800 – 1.500 TL  \n- Kontrol kablosu + ek muflar: 1.000 – 1.500 TL  \n- Yağmur sensörü (opsiyonel): 1.000 – 1.500 TL  \n→ **Toplam: 9.300 – 15.500 TL** (yağmur sensörü dahil)\n\n### GENEL TOPLAM (sadece malzeme, KDV hariç kabaca)\n\n- **Minimum:** 43.000 TL civarı  \n- **Maksimum:** 67.000 TL civarı  \n\nİşçilik, kazı, dolgu, test, programlama vb. için:\n- Genelde malzeme bedelinin **%60–100’ü** arası istenir.  \n- Anahtar teslim bir firma ile çalışırsan bu proje **60.000 – 100.000 TL** bandına oturabilir (özellikle pompa/kuuyu koşulları ve seçilecek marka segmenti fiyatı oynatır).\n\n---\n\n5) Montaj notları ve dikkat edilmesi gerekenler\n\n**1) Kuyu ve pompa**\n- Pompayı kuyu tabanına “oturtma”, dipten en az 1,5–2 m yukarıda as.  \n- Kuyu derinliği + dinamik seviye bilgisine göre pompanın basma yüksekliği mutlaka kontrol edilmeli.  \n- Kuyu çok kum getiriyorsa ilave kum filtresi veya kuyu geliştirme (temizleme) yaptırmak mantıklı.\n\n**2) Boru döşeme**\n- Kazı derinliği: En az 25–30 cm (Konya’da don riski zayıf ama mekanik darbeden korunur).  \n- Ana hat (32 mm) mümkün olduğunca düz ve kısa olsun; gereksiz dirsekten kaçın.  \n- Sprink hatlarını “döngü” (ring) şeklinde bağlamak basınç dağılımını iyileştirir (imkân varsa).\n\n**3) Sprink yerleşimi ve ayarı**\n- “Baş-başa sulama” kuralı: Bir sprink, komşu sprink’in ayağına kadar su atmalı.  \n- L şekilli alanlarda kuru nokta kalmaması için:\n  - Köşelere mutlaka 90° nozullar,  \n  - İç köşelerde ayarlı HE-VAN nozullar kullan.  \n- Sprink yükseklik ayarı: Üst kapak, çim seviyesinin 1–2 cm altında kalmalı.\n\n**4) Damla sulama**\n- Damla hortumlar:\n  - Toprak yüzeyine ya da çok az (5–10 cm) toprağa gömülü uygulanabilir. Yüzeyde ise mutlaka çimden/biçiciden uzak hatlarda gitsin.  \n- Ağacın kök tacı etrafında 1–2 tur damla hortum döndürmek, tek noktaya su vermekten daha sağlıklıdır.  \n- Damla zonlarında mutlaka filtre temiz tutulmalı; tıkanma riski yüksektir.\n\n**5) Filtre ve kolektör**\n- Filtreyi, kolay ulaşılabilir bir noktaya (genelde kolektörün hemen önüne) koy.  \n- İlk aylar her hafta, sonra 2–3 haftada bir disk filtresini söküp temizlemeyi ihmal etme.  \n- Kolektör (solenoid vanaların olduğu grup), vana kutusu içinde, üstü toprakla kapalı, ama her zaman erişilebilir olmalı.\n\n**6) Otomasyon ve elektrik**\n- Kontrol ünitesini yağmur almayan bir yere (örneğin garaj, teras altı, kapalı veranda) koy.  \n- Kablo eklerini mutlaka su geçirmez mufla yap; sadece bant sarma uzun vadede sorun çıkarır.  \n- Pompa panosunun topraklaması düzgün olmalı; sigorta/kaçak akım rölesi mutlaka olsun.\n\n**7) Programlama (Konya Ereğli yaz ayları için başlangıç ayarı)**  \n- Çim zonları (Zone 1–2):  \n  - Her gün 1 kez, sabah 04:00–06:00 arası  \n  - 10–15 dk/zone  \n  - Aşırı sıcak/gün kurak giderse sabah + akşamüstü 5–8 dk şeklinde 2’ye bölünebilir.\n- Damla zonları (Zone 3–4):  \n  - Haftada 3 gün (ör. Pazartesi–Çarşamba–Cuma)  \n  - 45–60 dk/zone (toprağın su tutma durumuna göre artır/azalt)  \n\n**8) Test ve ince ayar**\n- İlk devreye almada:\n  - Her zonu tek tek çalıştır, basınç düşümü ve kaplama alanını gözle.  \n  - Kuru bölgeler kalıyorsa nozulların açı/yarıçap ayarını düzelt veya gerekiyorsa 1–2 sprink ekle.  \n  - Damla hatlarında sızıntı/kopma var mı mutlaka kontrol et.\n\n---\n\nİstersen bir sonraki adımda:\n- Basit bir kroki (elle çizip foto atabileceğini varsayarak)  \n- Kuyu derinliği ve su seviyesi (tahmini bile olur)  \n\npaylaşırsan, sprink adedi ve hat metrajlarını “tam senin bahçene özel” netleştirip, dilersen daha ekonomik (örn. damla ve boruda Poelsan ağırlıklı) ve daha premium (tam Rain Bird/Netafim ağırlıklı) iki alternatif liste de çıkarabilirim.",
        "rawInput": {
          "alan_m2": "200",
          "bahce_sekli": "L şekilli",
          "su_kaynagi": "kuyu",
          "sistem_tipi": "karışık",
          "otomasyon": "evet, tam otomatik",
          "lokasyon": "",
          "notlar": ""
        }
      }
    ]
  },
  {
    "email": "guest@sulamaasistani.local",
    "password": "",
    "limit": 9999,
    "used": 82,
    "memory": [
      {
        "role": "user",
        "content": "Bahçe için elimde şu ön bilgiler var:\n - Alan: 200 m²\n - Şekil: dikdörtgen\n - Su kaynağı: şebeke suyu\n - Sistem tipi: rotor\n - Otomasyon: tam otomatik\n\nKURAL: Bu mesaja EN FAZLA 3 cümleyle kısa cevap ver.\nMadde, başlık, tablo, uzun teknik açıklama, fiyat listesi YASAK.\nGerekiyorsa sadece 1 tane netleştirici soru sor, sonra dur.\n\nKULLANICI MESAJI:\ndetaylandır"
      },
      {
        "role": "assistant",
        "content": "Rotor yerleşimini şöyle düşünebilirsin: Dikdörtgen bahçenin dört köşesine 4 rotor, uzun kenarlar boyunca aralara karşılıklı gelecek şekilde 2’şer rotor daha koyup toplam 12 rotoru “kareleme” mantığıyla, atış yarıçapları birbirine değecek şekilde dizmelisin. Ağaçlar için sağ kenara paralel 1 hat, sol kenara paralel 1 hat 16 mm damla boru çekip her ağacın etrafına halka gibi dönerek ağaç başına 2–3 damlatıcı (veya entegre damla borudan 2–3 tur) vermelisin. Tam otomatik olması için de şebekeden gelen suyu önce 1\" filtreye, oradan 4’lü vana kolektörüne, oradan da ayrı ayrı 3 rotor zonu ve 1 damla zonuna dağıtıp kontrol ünitesini bu 4 vanaya bağlamalısın."
      },
      {
        "role": "user",
        "content": "Bahçe için elimde şu ön bilgiler var:\n - Alan: 200 m²\n - Şekil: dikdörtgen\n - Su kaynağı: şebeke suyu\n - Sistem tipi: rotor\n - Otomasyon: tam otomatik\n\nKURAL: Bu mesaja EN FAZLA 3 cümleyle kısa cevap ver.\nMadde, başlık, tablo, uzun teknik açıklama, fiyat listesi YASAK.\nGerekiyorsa sadece 1 tane netleştirici soru sor, sonra dur.\n\nKULLANICI MESAJI:\nbağlayalım"
      },
      {
        "role": "assistant",
        "content": "Bağlantı sırası basitçe şöyle olmalı: Şebeke çıkışı → vana (veya küresel vana) → 1\" mini filtre → 1\" kolektör (4 adet 1\" solenoid vana bağlı) → her vanadan ayrı ayrı PE100 32 mm ana hat → zone başında PE100 20 mm lateral ve üzerindeki rotorlar / damla hatları. Kontrol ünitesinden gelen sinyal kablolarını da (ortak nötr + her vana için bir renk) bu 4 solenoid vanaya bağlayıp, üniteyi priz olan iç mekâna alman yeterli."
      },
      {
        "role": "user",
        "content": "Bahçe için elimde şu ön bilgiler var:\n - Alan: 200 m²\n - Şekil: dikdörtgen\n - Su kaynağı: şebeke suyu\n - Sistem tipi: rotor\n - Otomasyon: tam otomatik\n\nKURAL: Kullanıcı net MALZEME LİSTESİ ve TEKLİF istiyor.\nGirizgah, özet, 'istersen', 'bir sonraki adımda' gibi cümleler YASAK.\nCevap formatın ŞÖYLE OLACAK:\n1) En fazla 1 cümlelik çok kısa özet.\n2) Hemen altında madde madde liste; her satırda: 'Adet x Ürün adı – kısa açıklama – Yaklaşık fiyat (X TL)'. En fazla 20 satır.\n3) Listenin en altında tek satırda: 'Toplam yaklaşık: X–Y TL (malzeme, işçilik hariç/dahil)'.\nBaşka açıklama, soru, davet YAZMA.\n\nKULLANICI MESAJI:\ntamam bana malzeme listesini ver"
      },
      {
        "role": "assistant",
        "content": "200 m² dikdörtgen, hafif eğimli ve 11 meyve ağaçlı bahçe için 3 zone rotor + 1 zone damla, tam otomatik sulama malzeme listesi ve yaklaşık maliyet aşağıdadır:\n\n1) 12 x Rain Bird 3504 rotor sprinkler – çim alan için orta menzil rotor başlık – Yaklaşık fiyat (12 × 420 TL ≈ 5.040 TL)  \n2) 4 x Rain Bird 100 DV 1\" 24V solenoid vana – 3 rotor zonu + 1 damla zonu için otomatik vana – Yaklaşık fiyat (4 × 1.188 TL ≈ 4.752 TL)  \n3) 1 x Rain Bird RC2 6 istasyon iç mekân kontrol ünitesi – 4 zone’u yöneten WiFi’li otomasyon paneli – Yaklaşık fiyat (≈ 5.000 TL)  \n4) 1 x Arangül 12\"/14\" vana kutusu – solenoid vanaların yer altı montajı ve korunması – Yaklaşık fiyat (≈ 970 TL)  \n5) 40 m x PE100 Kangal Boru 32 mm 10 ATÜ – ana hat borusu (şebekeden kolektöre ve zon başlarına) – Yaklaşık fiyat (40 × 24 TL ≈ 960 TL)  \n6) 80 m x PE100 Kangal Boru 20 mm 16 ATÜ – rotor ve damla lateralleri için hat borusu – Yaklaşık fiyat (80 × 13,9 TL ≈ 1.110 TL)  \n7) 80 m x 16 mm entegre damla boru (16x40 veya 16x50 cm) – sağ/sol kenardaki 11 ağacı çevreleyen damla halkaları – Yaklaşık fiyat (80 × 4,4 TL ≈ 350 TL)  \n8) 30 x Basınç ayarlı damlatıcı 4 L/saat – ağaç başına 2–3 noktasal damlatıcı takviyesi – Yaklaşık fiyat (30 × 2,6 TL ≈ 80 TL)  \n9) 1 x Plastik mini filtre 1\" (Serdrip) – tüm sistemi tortu ve pislikten koruyan ana filtre – Yaklaşık fiyat (≈ 180 TL)  \n10) 1 x Basınç düşürücü 3/4\" (Kalde) – damla zonu basıncını uygun seviyeye indiren regülatör – Yaklaşık fiyat (≈ 900 TL)  \n11) 1 x MTT100 kolektör gövdesi + 4 lü nipel seti – 4 adet solenoid vana için manifold – Yaklaşık fiyat (≈ 300 TL)  \n12) 12 x 32 mm priz kolye – her rotor için ana hattan branşman çıkışı – Yaklaşık fiyat (12 × 38 TL ≈ 460 TL)  \n13) 24 x 20 × 1/2\" kaplin dış dişli dirsek – priz kopyeden PE20’ye ve rotora dönüşlü bağlantı – Yaklaşık fiyat (24 × 18 TL ≈ 430 TL)  \n14) 20 x PE kaplin/dirsek/TE (20 ve 32 mm karışık) – hat dönüşleri, ek ve ana/yan hat dağıtımları – Yaklaşık fiyat (≈ 600 TL)  \n15) 1 x Sulama sinyal kablosu 7 damarlı (SSK7, 50 m) – kontrol ünitesinden 4 solenoid vanaya kumanda kablosu – Yaklaşık fiyat (50 × 45,5 TL ≈ 2.275 TL)  \n16) 1 x Teflon bant Veron küçük (2’li almak mantıklı) – tüm dişli bağlantılarda sızdırmazlık – Yaklaşık fiyat (≈ 30 TL)  \n17) 20 x Damlama kazığı / gözlük tapa / küçük damla fittings karışık – damla hatlarının sabitlenmesi ve uç kapama – Yaklaşık fiyat (≈ 150 TL)  \n18) 1 x Klasik boru kesme makası 16–42 mm (Arangül veya SGS) – PE ve damla borularını düzgün kesmek için – Yaklaşık fiyat (≈ 580 TL)  \n\nToplam yaklaşık: 22.000–26.000 TL (malzeme, işçilik hariç)."
      },
      {
        "role": "user",
        "content": "Bahçe için elimde şu ön bilgiler var:\n - Alan: 200 m²\n - Şekil: dikdörtgen\n - Su kaynağı: şebeke suyu\n - Sistem tipi: rotor\n - Otomasyon: tam otomatik\n\nKURAL: Bu mesaja EN FAZLA 3 cümleyle kısa cevap ver.\nMadde, başlık, tablo, uzun teknik açıklama, fiyat listesi YASAK.\nGerekiyorsa sadece 1 tane netleştirici soru sor, sonra dur.\n\nKULLANICI MESAJI:\ndevam et"
      },
      {
        "role": "assistant",
        "content": "Bu kurduğumuz planda artık yapılacaklar; boru güzergâhını ve rotor–damla hatlarının yerlerini arazi üzerine ip/spreyle işaretlemek, sonra PE32 ana hat ve PE20 lateralleri gömüp rotor ve damla hatlarını bağlamak. En son adımda kontrol ünitesi, solenoid vanalar ve sinyal kablosu bağlantılarını yapıp her zone’u tek tek denemen yeterli olur. İstersen şimdi \"kazı derinliği ve boru döşeme mesafelerini\" de 2–3 cümlede netleştirebiliriz."
      },
      {
        "role": "user",
        "content": "Bahçe için elimde şu ön bilgiler var:\n - Alan: 200 m²\n - Şekil: dikdörtgen\n - Su kaynağı: şebeke suyu\n - Sistem tipi: rotor\n - Otomasyon: tam otomatik\n\nKURAL: Bu mesaja EN FAZLA 3 cümleyle kısa cevap ver.\nMadde, başlık, tablo, uzun teknik açıklama, fiyat listesi YASAK.\nGerekiyorsa sadece 1 tane netleştirici soru sor, sonra dur.\n\nKULLANICI MESAJI:\nnetleştir"
      },
      {
        "role": "assistant",
        "content": "Boru ve sprink hatlarını çim altında don riski yoksa yaklaşık 25–30 cm derine, rotor gövdeleri üst kapak çim seviyesine gelecek şekilde gömmen yeterli olur. Rotorlar arasında, seçtiğin nozulun 7–10 m civarı atış yarıçapına göre “kafa kafaya sulama” olacak biçimde (yani her rotor diğerine su atacak şekilde) mesafe bırakmalısın. Damla hatlarını ise genelde 5–10 cm derine veya yüzeyde malç altında, ağaç gövdelerinden 40–60 cm uzağa halka gibi döşemen iyi olur."
      },
      {
        "role": "user",
        "content": "Bahçe için elimde şu ön bilgiler var:\n - Alan: 200 m²\n - Şekil: dikdörtgen\n - Su kaynağı: şebeke suyu\n - Sistem tipi: rotor\n - Otomasyon: tam otomatik\n\nKURAL: Kullanıcı net MALZEME LİSTESİ ve TEKLİF istiyor.\nGirizgah, özet, 'istersen', 'bir sonraki adımda' gibi cümleler YASAK.\nCevap formatın ŞÖYLE OLACAK:\n1) En fazla 1 cümlelik çok kısa özet.\n2) Hemen altında madde madde liste; her satırda: 'Adet x Ürün adı – kısa açıklama – Yaklaşık fiyat (X TL)'. En fazla 20 satır.\n3) Listenin en altında tek satırda: 'Toplam yaklaşık: X–Y TL (malzeme, işçilik hariç/dahil)'.\nBaşka açıklama, soru, davet YAZMA.\n\nKULLANICI MESAJI:\nmalzeme listesi çıkar"
      },
      {
        "role": "assistant",
        "content": "200 m² dikdörtgen bahçe, 3 zone rotor + 1 zone damla, tam otomatik sistem için temel malzeme listesi ve yaklaşık maliyet:\n\n1) 12 x Rain Bird 3504 rotor sprinkler – çim alan için orta menzil rotor başlık – Yaklaşık fiyat (12 × 420 TL ≈ 5.040 TL)  \n2) 4 x Rain Bird 100 DV 1\" 24V solenoid vana – 3 rotor zonu + 1 damla zonu için otomatik vana – Yaklaşık fiyat (4 × 1.188 TL ≈ 4.752 TL)  \n3) 1 x Rain Bird RC2 6 istasyon iç mekân kontrol ünitesi – 4 zone’u yöneten WiFi’li otomasyon paneli – Yaklaşık fiyat (≈ 5.000 TL)  \n4) 1 x Arangül 12\"/14\" vana kutusu – solenoid vanaların yer altı montajı ve korunması – Yaklaşık fiyat (≈ 970 TL)  \n5) 40 m x PE100 Kangal Boru 32 mm 10 ATÜ – ana hat borusu (şebekeden kolektöre ve zon başlarına) – Yaklaşık fiyat (40 × 24 TL ≈ 960 TL)  \n6) 80 m x PE100 Kangal Boru 20 mm 16 ATÜ – rotor ve damla lateralleri için hat borusu – Yaklaşık fiyat (80 × 13,9 TL ≈ 1.110 TL)  \n7) 80 m x 16 mm entegre damla boru (16x40 veya 16x50 cm) – sağ/sol kenardaki 11 ağacı çevreleyen damla halkaları – Yaklaşık fiyat (80 × 4,4 TL ≈ 350 TL)  \n8) 30 x Basınç ayarlı damlatıcı 4 L/saat – ağaç başına 2–3 noktasal damlatıcı takviyesi – Yaklaşık fiyat (30 × 2,6 TL ≈ 80 TL)  \n9) 1 x Plastik mini filtre 1\" (Serdrip) – tüm sistemi tortu ve pislikten koruyan ana filtre – Yaklaşık fiyat (≈ 180 TL)  \n10) 1 x Basınç düşürücü 3/4\" – damla zonu basıncını uygun seviyeye indiren regülatör – Yaklaşık fiyat (≈ 900 TL)  \n11) 1 x MTT100 kolektör gövdesi + 4 lü nipel seti – 4 adet solenoid vana için manifold – Yaklaşık fiyat (≈ 300 TL)  \n12) 12 x 32 mm priz kolye – her rotor için ana hattan branşman çıkışı – Yaklaşık fiyat (12 × 38 TL ≈ 460 TL)  \n13) 24 x 20 × 1/2\" kaplin dış dişli dirsek – priz kolyeden PE20’ye ve rotora dönüşlü bağlantı – Yaklaşık fiyat (24 × 18 TL ≈ 430 TL)  \n14) 20 x PE kaplin/dirsek/TE (20 ve 32 mm karışık) – hat dönüşleri, ek ve ana/yan hat dağıtımları – Yaklaşık fiyat (≈ 600 TL)  \n15) 1 x Sulama sinyal kablosu 7 damarlı (SSK7, 50 m) – kontrol ünitesinden 4 solenoid vanaya kumanda kablosu – Yaklaşık fiyat (50 × 45,5 TL ≈ 2.275 TL)  \n16) 1 x Teflon bant Veron küçük (2’li almak mantıklı) – tüm dişli bağlantılarda sızdırmazlık – Yaklaşık fiyat (≈ 30 TL)  \n17) 20 x Damlama kazığı / gözlük tapa / küçük damla fittings karışık – damla hatlarının sabitlenmesi ve uç kapama – Yaklaşık fiyat (≈ 150 TL)  \n18) 1 x Klasik boru kesme makası 16–42 mm – PE ve damla borularını düzgün kesmek için – Yaklaşık fiyat (≈ 580 TL)  \n\nToplam yaklaşık: 22.000–26.000 TL (malzeme, işçilik hariç)."
      },
      {
        "role": "user",
        "content": "Bahçe için elimde şu ön bilgiler var:\n - Alan: 200 m²\n - Şekil: dikdörtgen\n - Su kaynağı: şebeke suyu\n - Sistem tipi: sprink\n - Otomasyon: tam otomatik\n\nKURAL: Kullanıcı net MALZEME LİSTESİ ve TEKLİF istiyor.\nGirizgah, özet, 'istersen', 'bir sonraki adımda' gibi cümleler YASAK.\nCevap formatın ŞÖYLE OLACAK:\n1) En fazla 1 cümlelik çok kısa özet.\n2) Hemen altında madde madde liste; her satırda: 'Adet x Ürün adı – kısa açıklama – Yaklaşık fiyat (X TL)'. En fazla 20 satır.\n3) Listenin en altında tek satırda: 'Toplam yaklaşık: X–Y TL (malzeme, işçilik hariç/dahil)'.\nBaşka açıklama, soru, davet YAZMA.\n\nKULLANICI MESAJI:\nmalzeme listesi çıkar"
      },
      {
        "role": "assistant",
        "content": "200 m² dikdörtgen bahçe için 3 zone sprey sprink + tam otomatik sistem temel malzeme listesi ve yaklaşık maliyet:\n\n1) 12 x Rain Bird 1804 sprey gövde 10 cm – çim için klasik pop-up sprey gövde – Yaklaşık fiyat (12 × 126 TL ≈ 1.500 TL)  \n2) 12 x Rain Bird VAN 12 nozül – 3,5–4 m menzilli ayarlı sprey nozulu – Yaklaşık fiyat (12 × 65 TL ≈ 780 TL)  \n3) 4 x Rain Bird 100 DV 1\" 24V solenoid vana – 3 sprey zonu + gerekirse 1 yedek/ilave zone için otomatik vana – Yaklaşık fiyat (4 × 1.188 TL ≈ 4.752 TL)  \n4) 1 x Rain Bird RC2 6 istasyon iç mekân kontrol ünitesi – 4 zone’u yöneten WiFi’li otomasyon paneli – Yaklaşık fiyat (≈ 5.000 TL)  \n5) 1 x Arangül 12\"/14\" vana kutusu – solenoid vanaların yer altı montajı ve korunması – Yaklaşık fiyat (≈ 970 TL)  \n6) 40 m x PE100 Kangal Boru 32 mm 10 ATÜ – ana hat borusu (şebekeden kolektöre ve zon başlarına) – Yaklaşık fiyat (40 × 24 TL ≈ 960 TL)  \n7) 80 m x PE100 Kangal Boru 20 mm 16 ATÜ – sprey lateralleri için hat borusu – Yaklaşık fiyat (80 × 13,9 TL ≈ 1.110 TL)  \n8) 1 x Plastik mini filtre 1\" (Serdrip) – tüm sistemi tortu ve pislikten koruyan ana filtre – Yaklaşık fiyat (≈ 180 TL)  \n9) 1 x MTT100 kolektör gövdesi + 4 lü nipel seti – 4 adet solenoid vana için manifold – Yaklaşık fiyat (≈ 300 TL)  \n10) 12 x 32 mm priz kolye – her sprey için ana hattan branşman çıkışı – Yaklaşık fiyat (12 × 38 TL ≈ 460 TL)  \n11) 24 x 20 × 1/2\" kaplin dış dişli dirsek – priz kolyeden PE20’ye ve spreylere dönüşlü bağlantı – Yaklaşık fiyat (24 × 18 TL ≈ 430 TL)  \n12) 20 x PE kaplin/dirsek/TE (20 ve 32 mm karışık) – hat dönüşleri, ek ve ana/yan hat dağıtımları – Yaklaşık fiyat (≈ 600 TL)  \n13) 1 x Sulama sinyal kablosu 7 damarlı (SSK7, 50 m) – kontrol ünitesinden 4 solenoid vanaya kumanda kablosu – Yaklaşık fiyat (50 × 45,5 TL ≈ 2.275 TL)  \n14) 1 x Teflon bant Veron küçük (2’li almak mantıklı) – tüm dişli bağlantılarda sızdırmazlık – Yaklaşık fiyat (≈ 30 TL)  \n15) 1 x Klasik boru kesme makası 16–42 mm – PE borularını düzgün kesmek için – Yaklaşık fiyat (≈ 580 TL)  \n\nToplam yaklaşık: 18.000–22.000 TL (malzeme, işçilik hariç)."
      },
      {
        "role": "user",
        "content": "Bahçe için elimde şu ön bilgiler var:\n - Alan: 200 m²\n - Şekil: dikdörtgen\n - Su kaynağı: şebeke suyu\n - Sistem tipi: rotor\n - Otomasyon: tam otomatik\n\nKURAL: Bu mesaja EN FAZLA 3 cümleyle kısa cevap ver.\nMadde, başlık, tablo, uzun teknik açıklama, fiyat listesi YASAK.\nGerekiyorsa sadece 1 tane netleştirici soru sor, sonra dur.\n\nKULLANICI MESAJI:\n11 adet ağaç var, hafif eğim var"
      },
      {
        "role": "assistant",
        "content": "Bu bilgilerle en mantıklı kurulum, çim alanı 3 zone rotorla, 11 ağacı ise ayrı 1 zone damla sulama ile beslemek (toplam 4 zone) olacaktır. Ana hatlarda PE100 32 mm, tüm rotor ve damla laterallerinde PE100 20 mm kullanıp 4 adet 1\" solenoid vana ve en az 4 istasyonlu kontrol ünitesiyle tam otomatik sistemi kurabilirsin. Ağaçlar aynı hatta sıralı mı (sağ/sol kenar boyunca), yoksa bahçeye dağınık mı?"
      },
      {
        "role": "user",
        "content": "Bahçe için elimde şu ön bilgiler var:\n - Alan: 200 m²\n - Şekil: dikdörtgen\n - Su kaynağı: şebeke suyu\n - Sistem tipi: rotor\n - Otomasyon: tam otomatik\n\nKURAL: Bu mesaja EN FAZLA 3 cümleyle kısa cevap ver.\nMadde, başlık, tablo, uzun teknik açıklama, fiyat listesi YASAK.\nGerekiyorsa sadece 1 tane netleştirici soru sor, sonra dur.\n\nKULLANICI MESAJI:\n6 sağda, 5 solda"
      },
      {
        "role": "assistant",
        "content": "Ağaçların 6’sı sağ kenarda, 5’i sol kenarda olduğu için çimi 3 zone rotorla, iki kenar boyunca giden tek bir damla hattını da 1 ayrı zone olarak planlamak en pratik çözümdür. Sağ ve sol kenara, çim rotorlardan biraz dışta kalacak şekilde 16 mm damla boruyu paralel döşeyip her ağaca 2–3 damlatıcı veya 1–2 tur entegre damla boru vermelisin. Rotorlar ve damla hattı için ana hat yine PE100 32 mm, tüm lateraller PE100 20 mm kalabilir."
      },
      {
        "role": "user",
        "content": "Bahçe için elimde şu ön bilgiler var:\n - Alan: 200 m²\n - Şekil: dikdörtgen\n - Su kaynağı: şebeke suyu\n - Sistem tipi: rotor\n - Otomasyon: tam otomatik\n\nKURAL: Bu mesaja EN FAZLA 3 cümleyle kısa cevap ver.\nMadde, başlık, tablo, uzun teknik açıklama, fiyat listesi YASAK.\nGerekiyorsa sadece 1 tane netleştirici soru sor, sonra dur.\n\nKULLANICI MESAJI:\nfiyat teklifi ver"
      },
      {
        "role": "assistant",
        "content": "Bu tipte 4 zonlu (3 rotor + 1 damla) tam otomatik sistem için malzeme toplamı kabaca 18.000–22.000 TL bandında olur (işçilik hariç). İşçiliği de bir firma yaparsa, kazı, boru döşeme ve montajla birlikte genelde malzemenin yaklaşık 1–1,5 katı kadar ek maliyet çıkabilir. Şebeke basıncın çok zayıfsa ek olarak küçük bir hidrofor ihtiyacı da doğabilir, bu da 6.000–10.000 TL civarı ekstra bir kalem olur."
      },
      {
        "role": "user",
        "content": "Bahçe için elimde şu ön bilgiler var:\n - Alan: 200 m²\n - Şekil: dikdörtgen\n - Su kaynağı: şebeke suyu\n - Sistem tipi: rotor\n - Otomasyon: tam otomatik\n\nKURAL: Kullanıcı net MALZEME LİSTESİ ve TEKLİF istiyor.\nGirizgah, özet, 'istersen', 'bir sonraki adımda' gibi cümleler YASAK.\nCevap formatın ŞÖYLE OLACAK:\n1) En fazla 1 cümlelik çok kısa özet.\n2) Hemen altında madde madde liste; her satırda: 'Adet x Ürün adı – kısa açıklama – Yaklaşık fiyat (X TL)'. En fazla 20 satır.\n3) Listenin en altında tek satırda: 'Toplam yaklaşık: X–Y TL (malzeme, işçilik hariç/dahil)'.\nBaşka açıklama, soru, davet YAZMA.\n\nKULLANICI MESAJI:\nmalzeme listesi ile birlikte yanlarında fiyat yazan liste ver"
      },
      {
        "role": "assistant",
        "content": "200 m² dikdörtgen, 3 zone rotor + 1 zone damla, tam otomatik sistem için temel malzeme listesi ve yaklaşık maliyet:\n\n1) 12 x Rain Bird 3504 rotor sprinkler – çim alan için orta menzil rotor başlık – Yaklaşık fiyat (12 × 420 TL ≈ 5.040 TL)  \n2) 4 x Rain Bird 100 DV 1\" 24V solenoid vana – 3 rotor zonu + 1 damla zonu için otomatik vana – Yaklaşık fiyat (4 × 1.188 TL ≈ 4.752 TL)  \n3) 1 x Rain Bird RC2 6 istasyon iç mekân kontrol ünitesi – 4 zone’u yöneten WiFi’li otomasyon paneli – Yaklaşık fiyat (≈ 5.000 TL)  \n4) 1 x Arangül 12\"/14\" vana kutusu – solenoid vanaların yer altı montajı ve korunması – Yaklaşık fiyat (≈ 970 TL)  \n5) 40 m x PE100 Kangal Boru 32 mm 10 ATÜ – ana hat borusu (şebekeden kolektöre ve zon başlarına) – Yaklaşık fiyat (40 × 24 TL ≈ 960 TL)  \n6) 80 m x PE100 Kangal Boru 20 mm 16 ATÜ – rotor ve damla lateralleri için hat borusu – Yaklaşık fiyat (80 × 13,92 TL ≈ 1.115 TL)  \n7) 80 m x 16 mm entegre damla boru (16x40 veya 16x50 cm) – sağ/sol kenardaki 11 ağacı çevreleyen damla halkaları – Yaklaşık fiyat (80 × 4,36 TL ≈ 350 TL)  \n8) 30 x Basınç ayarlı damlatıcı 4 L/saat – ağaç başına ek noktasal damlatıcı (gerekirse) – Yaklaşık fiyat (30 × 2,62 TL ≈ 80 TL)  \n9) 1 x Plastik mini filtre 1\" (Serdrip) – tüm sistemi tortu ve pislikten koruyan ana filtre – Yaklaşık fiyat (≈ 181 TL)  \n10) 1 x Basınç düşürücü 3/4\" (Kalde) – damla zonu basıncını uygun seviyeye indiren regülatör – Yaklaşık fiyat (≈ 900 TL)  \n11) 1 x MTT100 kolektör gövdesi + bağlantı fittingsleri – 4 adet solenoid vana için manifold – Yaklaşık fiyat (≈ 300 TL)  \n12) 12 x 32 mm priz kolye – her rotor için PE32 ana hattan branşman çıkışı – Yaklaşık fiyat (12 × 38 TL ≈ 460 TL)  \n13) 24 x 20 × 1/2\" kaplin dış dişli dirsek – priz kolyeden PE20’ye ve rotora dönüşlü bağlantı – Yaklaşık fiyat (24 × 18,5 TL ≈ 445 TL)  \n14) 20 x PE kaplin/dirsek/TE (20 ve 32 mm karışık) – hat dönüşleri, ek ve ana/yan hat dağıtımları – Yaklaşık fiyat (≈ 600 TL)  \n15) 1 x Sulama sinyal kablosu 7 damarlı (SSK7, 50 m) – kontrol ünitesinden 4 solenoid vanaya kumanda kablosu – Yaklaşık fiyat (50 × 45,54 TL ≈ 2.275 TL)  \n16) 1 x Veron teflon bant küçük (2 rulo düşün) – tüm dişli bağlantılarda sızdırmazlık – Yaklaşık fiyat (≈ 28 TL)  \n17) 20 x Damlama kazığı / gözlük tapa / küçük damla fittings karışık – damla hatlarının sabitlenmesi ve uç kapama – Yaklaşık fiyat (≈ 150 TL)  \n18) 1 x Klasik boru kesme makası 16–42 mm (Arangül veya SGS) – PE ve damla borularını düzgün kesmek için – Yaklaşık fiyat (≈ 580 TL)  \n\nToplam yaklaşık: 22.000–26.000 TL (malzeme, işçilik hariç)."
      },
      {
        "role": "user",
        "content": "Bahçe için elimde şu ön bilgiler var:\n - Alan: 200 m²\n - Şekil: dikdörtgen\n - Su kaynağı: şebeke suyu\n - Sistem tipi: sprink\n - Otomasyon: tam otomatik\n\nKURAL: Kullanıcı net MALZEME LİSTESİ ve TEKLİF istiyor.\nGirizgah, özet, 'istersen', 'bir sonraki adımda' gibi cümleler YASAK.\nCevap formatın ŞÖYLE OLACAK:\n1) En fazla 1 cümlelik çok kısa özet.\n2) Hemen altında madde madde liste; her satırda: 'Adet x Ürün adı – kısa açıklama – Yaklaşık fiyat (X TL)'. En fazla 20 satır.\n3) Listenin en altında tek satırda: 'Toplam yaklaşık: X–Y TL (malzeme, işçilik hariç/dahil)'.\nBaşka açıklama, soru, davet YAZMA.\n\nKULLANICI MESAJI:\nfiyatlı malzeme listesi çıkar"
      },
      {
        "role": "assistant",
        "content": "200 m² dikdörtgen bahçe için 3 zone sprey sprink + tam otomatik sistem temel malzeme listesi ve yaklaşık maliyet:\n\n1) 12 x Rain Bird 1804 sprey gövde 10 cm – çim için klasik pop-up sprey gövde – Yaklaşık fiyat (12 × 126 TL ≈ 1.500 TL)  \n2) 12 x Rain Bird VAN 12 nozül – 3,5–4 m menzilli ayarlı sprey nozulu – Yaklaşık fiyat (12 × 65 TL ≈ 780 TL)  \n3) 4 x Rain Bird 100 DV 1\" 24V solenoid vana – 3 sprey zonu + 1 yedek/ilave zone için otomatik vana – Yaklaşık fiyat (4 × 1.188 TL ≈ 4.752 TL)  \n4) 1 x Rain Bird RC2 6 istasyon iç mekân kontrol ünitesi – 4 zone’u yöneten WiFi’li otomasyon paneli – Yaklaşık fiyat (≈ 5.000 TL)  \n5) 1 x Arangül 12\"/14\" vana kutusu – solenoid vanaların yer altı montajı ve korunması – Yaklaşık fiyat (≈ 970 TL)  \n6) 40 m x PE100 Kangal Boru 32 mm 10 ATÜ – ana hat borusu (şebekeden kolektöre ve zon başlarına) – Yaklaşık fiyat (40 × 24 TL ≈ 960 TL)  \n7) 80 m x PE100 Kangal Boru 20 mm 16 ATÜ – sprey lateralleri için hat borusu – Yaklaşık fiyat (80 × 13,92 TL ≈ 1.115 TL)  \n8) 1 x Plastik mini filtre 1\" (Serdrip) – sistemi tortu ve pislikten koruyan ana filtre – Yaklaşık fiyat (≈ 181 TL)  \n9) 1 x MTT100 kolektör gövdesi + bağlantı fittingsleri – 4 adet solenoid vana için manifold – Yaklaşık fiyat (≈ 300 TL)  \n10) 12 x 32 mm priz kolye – her sprey için PE32 ana hattan branşman çıkışı – Yaklaşık fiyat (12 × 38 TL ≈ 460 TL)  \n11) 24 x 20 × 1/2\" kaplin dış dişli dirsek – priz kolyeden PE20’ye ve spreylere dönüşlü bağlantı – Yaklaşık fiyat (24 × 18,5 TL ≈ 445 TL)  \n12) 20 x PE kaplin/dirsek/TE (20 ve 32 mm karışık) – hat dönüşleri, ek ve ana/yan hat dağıtımları – Yaklaşık fiyat (≈ 600 TL)  \n13) 1 x Sulama sinyal kablosu 7 damarlı (SSK7, 50 m) – kontrol ünitesinden 4 solenoid vanaya kumanda kablosu – Yaklaşık fiyat (50 × 45,54 TL ≈ 2.275 TL)  \n14) 1 x Veron teflon bant küçük (2 rulo düşün) – tüm dişli bağlantılarda sızdırmazlık – Yaklaşık fiyat (≈ 28 TL)  \n15) 1 x Klasik boru kesme makası 16–42 mm – PE borularını düzgün kesmek için – Yaklaşık fiyat (≈ 580 TL)  \n\nToplam yaklaşık: 18.000–22.000 TL (malzeme, işçilik hariç)."
      },
      {
        "role": "user",
        "content": "Bahçe için elimde şu ön bilgiler var:\n - Alan: 200 m²\n - Şekil: dikdörtgen\n - Su kaynağı: şebeke suyu\n - Sistem tipi: sprink\n - Otomasyon: tam otomatik\n\nKURAL: Kullanıcı net MALZEME LİSTESİ ve TEKLİF istiyor.\nGirizgah, özet, 'istersen', 'bir sonraki adımda' gibi cümleler YASAK.\nCevap formatın ŞÖYLE OLACAK:\n1) En fazla 1 cümlelik çok kısa özet.\n2) Hemen altında madde madde liste; her satırda: 'Adet x Ürün adı – kısa açıklama – Yaklaşık fiyat (X TL)'. En fazla 20 satır.\n3) Listenin en altında tek satırda: 'Toplam yaklaşık: X–Y TL (malzeme, işçilik hariç/dahil)'.\nBaşka açıklama, soru, davet YAZMA.\n\nKULLANICI MESAJI:\nmalzeme listesi çıkar"
      },
      {
        "role": "assistant",
        "content": "200 m² dikdörtgen çim alan için 3 zone sprey sprink + tam otomatik sistem temel malzeme listesi ve yaklaşık maliyet:\n\n1) 12 x Rain Bird 1804 sprey gövde 10 cm – çim için klasik pop-up sprey gövde – Yaklaşık fiyat (12 × 126 TL ≈ 1.500 TL)  \n2) 12 x Rain Bird VAN 12 nozül – 3,5–4 m menzilli ayarlı sprey nozulu – Yaklaşık fiyat (12 × 65 TL ≈ 780 TL)  \n3) 4 x Rain Bird 100 DV 1\" 24V solenoid vana – 3 sprey zonu + 1 yedek/ilave zone için otomatik vana – Yaklaşık fiyat (4 × 1.188 TL ≈ 4.752 TL)  \n4) 1 x Rain Bird RC2 6 istasyon iç mekân kontrol ünitesi – 4 zone’u yöneten WiFi’li otomasyon paneli – Yaklaşık fiyat (≈ 5.000 TL)  \n5) 1 x Arangül 12\"/14\" vana kutusu – solenoid vanaların yer altı montajı ve korunması – Yaklaşık fiyat (≈ 970 TL)  \n6) 40 m x PE100 Kangal Boru 32 mm 10 ATÜ – ana hat borusu (şebekeden kolektöre ve zon başlarına) – Yaklaşık fiyat (40 × 24 TL ≈ 960 TL)  \n7) 80 m x PE100 Kangal Boru 20 mm 16 ATÜ – sprink lateralleri için hat borusu – Yaklaşık fiyat (80 × 13,92 TL ≈ 1.115 TL)  \n8) 1 x Plastik mini filtre 1\" (Serdrip) – sistemi tortu ve pislikten koruyan ana filtre – Yaklaşık fiyat (≈ 181 TL)  \n9) 1 x MTT100 kolektör gövdesi + bağlantı fittingsleri – 4 adet solenoid vana için manifold – Yaklaşık fiyat (≈ 300 TL)  \n10) 12 x 32 mm priz kolye – her sprink için PE32 ana hattan branşman çıkışı – Yaklaşık fiyat (12 × 38 TL ≈ 460 TL)  \n11) 24 x 20 × 1/2\" kaplin dış dişli dirsek – priz kolyeden PE20’ye ve spreylere dönüşlü bağlantı – Yaklaşık fiyat (24 × 18,5 TL ≈ 445 TL)  \n12) 20 x PE kaplin/dirsek/TE (20 ve 32 mm karışık) – hat dönüşleri, ek ve ana/yan hat dağıtımları – Yaklaşık fiyat (≈ 600 TL)  \n13) 1 x Sulama sinyal kablosu 7 damarlı (SSK7, 50 m) – kontrol ünitesinden 4 solenoid vanaya kumanda kablosu – Yaklaşık fiyat (50 × 45,54 TL ≈ 2.275 TL)  \n14) 1 x Veron teflon bant küçük (2 rulo düşün) – tüm dişli bağlantılarda sızdırmazlık – Yaklaşık fiyat (≈ 28 TL)  \n15) 1 x Klasik boru kesme makası 16–42 mm – PE borularını düzgün kesmek için – Yaklaşık fiyat (≈ 580 TL)  \n\nToplam yaklaşık: 18.000–22.000 TL (malzeme, işçilik hariç)."
      },
      {
        "role": "user",
        "content": "Bahçe için elimde şu ön bilgiler var:\n - Alan: 200 m²\n - Şekil: dikdörtgen\n - Su kaynağı: kuyu\n - Sistem tipi: rotor\n - Otomasyon: tam otomatik\n\nKURAL: Bu mesaja EN FAZLA 3 cümleyle kısa cevap ver.\nMadde, başlık, tablo, uzun teknik açıklama, fiyat listesi YASAK.\nGerekiyorsa sadece 1 tane netleştirici soru sor, sonra dur.\n\nKULLANICI MESAJI:\n11 ağaç var, eğim az"
      },
      {
        "role": "assistant",
        "content": "Bu bilgilerle 3 zone rotor (çim) + 1 zone damla (11 ağaç) ve kuyu suyunun önüne filtre + mümkünse depo + hidrofor koyarak tam otomatik bir sistem kurmak en sağlıklısı olur. Ana hat için PE100 32 mm, tüm rotor ve damla lateraller için PE100 20 mm kullanıp 4 adet 1\" solenoid vana ve en az 4 istasyonlu kontrol ünitesi planlamalısın. Kuyudan mevcutta pompa/hidrofor var mı yoksa doğrudan dalgıçtan mı besleme düşünüyorsun?"
      },
      {
        "role": "user",
        "content": "Bahçe için elimde şu ön bilgiler var:\n - Alan: 200 m²\n - Şekil: dikdörtgen\n - Su kaynağı: kuyu\n - Sistem tipi: rotor\n - Otomasyon: tam otomatik\n\nKURAL: Bu mesaja EN FAZLA 3 cümleyle kısa cevap ver.\nMadde, başlık, tablo, uzun teknik açıklama, fiyat listesi YASAK.\nGerekiyorsa sadece 1 tane netleştirici soru sor, sonra dur.\n\nKULLANICI MESAJI:\ndoğrudan dalgıçla"
      },
      {
        "role": "assistant",
        "content": "Dalgıçtan doğrudan beslediğin için mutlaka çıkışa önce depo veya en azından iyi bir filtre + basınç regülatörü koyup, ordan PE100 32 mm ana hatla 3 rotor zone + 1 damla zone’a dağıtman gerekir. Rotor ve damla lateraller yine PE100 20 mm, 4 adet 1\" solenoid vana ve en az 4 istasyonlu otomasyon ile tam otomatik çalışır. Dalgıcın yaklaşık debi ve basıncını (örneğin m³/saat ve metre basma yüksekliği) biliyor musun?"
      },
      {
        "role": "user",
        "content": "Bahçe için elimde şu ön bilgiler var:\n - Alan: 200 m²\n - Şekil: dikdörtgen\n - Su kaynağı: kuyu\n - Sistem tipi: rotor\n - Otomasyon: tam otomatik\n\nKURAL: Bu mesaja EN FAZLA 3 cümleyle kısa cevap ver.\nMadde, başlık, tablo, uzun teknik açıklama, fiyat listesi YASAK.\nGerekiyorsa sadece 1 tane netleştirici soru sor, sonra dur.\n\nKULLANICI MESAJI:\nbilmiyorum"
      },
      {
        "role": "assistant",
        "content": "Debi/basıncı bilmediğimiz için güvenli tarafta kalıp 3 rotor zone’u küçük tutup (her zonda az sayıda rotor), ayrıca 1 damla zone ile toplam 4 zone’lu bir sistem kurmak gerekir. Kuyu suyu olduğu için dalgıç çıkışına mutlaka iyi bir filtre ve mümkünse küçük bir denge deposu + basınç şalterli kontrol koyup oradan PE100 32 mm ana hatla sulama kolektörüne gitmen doğru olur. İstersen bir sonraki adımda 4 zone’lu tam otomatik rotor + damla sistem için fiyatlı malzeme listesini yazabilirim."
      },
      {
        "role": "user",
        "content": "Bahçe için elimde şu ön bilgiler var:\n - Alan: 200 m²\n - Şekil: dikdörtgen\n - Su kaynağı: kuyu\n - Sistem tipi: rotor\n - Otomasyon: tam otomatik\n\nKURAL: Bu mesaja EN FAZLA 3 cümleyle kısa cevap ver.\nMadde, başlık, tablo, uzun teknik açıklama, fiyat listesi YASAK.\nGerekiyorsa sadece 1 tane netleştirici soru sor, sonra dur.\n\nKULLANICI MESAJI:\nyaz"
      },
      {
        "role": "assistant",
        "content": "200 m² dikdörtgen alan için 3 zone rotor (çim) + 1 zone damla (ağaçlar) ve kuyu beslemeli tam otomatik sistem mantıklı olur. Rotor ve damla laterallerinde PE100 20 mm, dalgıç sonrası ana hatta PE100 32 mm, kolektörde 4 adet 1\" solenoid vana ve en az 4 istasyonlu kontrol ünitesi yeterlidir. Kuyu suyu için dalgıç çıkışında iyi bir filtre ve mümkünse küçük bir denge deposu + basınç şalterli kontrol kullanman şart."
      },
      {
        "role": "user",
        "content": "Bahçe için elimde şu ön bilgiler var:\n - Alan: 200 m²\n - Şekil: dikdörtgen\n - Su kaynağı: kuyu\n - Sistem tipi: rotor\n - Otomasyon: tam otomatik\n\nKURAL: Bu mesaja EN FAZLA 3 cümleyle kısa cevap ver.\nMadde, başlık, tablo, uzun teknik açıklama, fiyat listesi YASAK.\nGerekiyorsa sadece 1 tane netleştirici soru sor, sonra dur.\n\nKULLANICI MESAJI:\nekle"
      },
      {
        "role": "assistant",
        "content": "Mevcut düzendeki tek ekleme, dalgıçtan sonra mutlaka bir filtre (tercihen disk filtre) ve basınç regülatörü/dengeli hidrofor ile sabit basınç sağlayıp ondan sonra PE100 32 mm ana hatla kolektöre gitmektir. Çim rotorlarda 3504 rotor, ağaçlarda 16 mm damla boru + basınç ayarlı damlatıcı kullanman hem debiyi hem de su tüketimini güvenli tutar. İhtiyaç olursa aynı kolektörden ileride ek rotor veya damla zone’u çıkarmak için 1 boş çıkış bırakmanı da öneririm."
      },
      {
        "role": "user",
        "content": "Bahçe için elimde şu ön bilgiler var:\n - Alan: 200 m²\n - Şekil: dikdörtgen\n - Su kaynağı: kuyu\n - Sistem tipi: rotor\n - Otomasyon: tam otomatik\n\nKURAL: Bu mesaja EN FAZLA 3 cümleyle kısa cevap ver.\nMadde, başlık, tablo, uzun teknik açıklama, fiyat listesi YASAK.\nGerekiyorsa sadece 1 tane netleştirici soru sor, sonra dur.\n\nKULLANICI MESAJI:\ntamam"
      },
      {
        "role": "assistant",
        "content": "4 zonlu (3 rotor + 1 damla) tam otomatik sistem tasarımını bu bilgilerle netleştirmiş olduk. Şimdi istersen bir sonraki adımda sadece fiyatlı veya sadece ürün isimli malzeme listesini ayrı ayrı yazabilirim."
      },
      {
        "role": "user",
        "content": "Bahçe için elimde şu ön bilgiler var:\n - Alan: 200 m²\n - Şekil: dikdörtgen\n - Su kaynağı: kuyu\n - Sistem tipi: rotor\n - Otomasyon: tam otomatik\n\nKURAL: Kullanıcı net MALZEME LİSTESİ ve TEKLİF istiyor.\nGirizgah, özet, 'istersen', 'bir sonraki adımda' gibi cümleler YASAK.\nCevap formatın ŞÖYLE OLACAK:\n1) En fazla 1 cümlelik çok kısa özet.\n2) Hemen altında madde madde liste; her satırda: 'Adet x Ürün adı – kısa açıklama – Yaklaşık fiyat (X TL)'. En fazla 20 satır.\n3) Listenin en altında tek satırda: 'Toplam yaklaşık: X–Y TL (malzeme, işçilik hariç/dahil)'.\nBaşka açıklama, soru, davet YAZMA.\n\nKULLANICI MESAJI:\nfiyatlı malzeme listesi çıkar"
      },
      {
        "role": "assistant",
        "content": "200 m² dikdörtgen bahçe için kuyu beslemeli 3 zone rotor + 1 zone damla, tam otomatik sistem temel malzeme listesi ve yaklaşık maliyet:\n\n1) 12 x Rain Bird 3504 rotor sprinkler – çim alan için orta menzil rotor başlık – Yaklaşık fiyat (12 × 420 TL ≈ 5.040 TL)  \n2) 4 x Rain Bird 100 DV 1\" 24V solenoid vana – 3 rotor zonu + 1 damla zonu için otomatik vana – Yaklaşık fiyat (4 × 1.188 TL ≈ 4.752 TL)  \n3) 1 x Rain Bird RC2 6 istasyon iç mekân kontrol ünitesi – 4 zone’u yöneten WiFi’li otomasyon paneli – Yaklaşık fiyat (≈ 5.000 TL)  \n4) 1 x Plastik mini filtre 1\" (Serdrip) – kuyu suyundaki tortuyu tutan ana filtre – Yaklaşık fiyat (≈ 181 TL)  \n5) 1 x Basınç düşürücü 3/4\" (Kalde) – dalgıçtan gelen yüksek basıncı sulama sistemine uygun seviyeye indirir – Yaklaşık fiyat (≈ 900 TL)  \n6) 40 m x PE100 Kangal Boru 32 mm 10 ATÜ – dalgıç çıkışı/filtre sonrası ana hat ve kolektör beslemesi – Yaklaşık fiyat (40 × 24 TL ≈ 960 TL)  \n7) 80 m x PE100 Kangal Boru 20 mm 16 ATÜ – tüm rotor ve damla lateralleri için boru hattı – Yaklaşık fiyat (80 × 13,92 TL ≈ 1.115 TL)  \n8) 80 m x 16 mm entegre damla boru (16x40–50 cm) – 11 ağacın çevresinde damla halkaları için – Yaklaşık fiyat (80 × 4,36 TL ≈ 350 TL)  \n9) 30 x Basınç ayarlı damlatıcı 4 L/saat – her ağaç için 2–3 noktasal damlatıcı – Yaklaşık fiyat (30 × 2,62 TL ≈ 80 TL)  \n10) 1 x MTT100 kolektör gövdesi + fittings – 4 solenoid vananın bağlandığı manifold – Yaklaşık fiyat (≈ 300 TL)  \n11) 1 x Arangül 12\"/14\" vana kutusu – kolektör ve solenoid vanaların yer altı montajı için – Yaklaşık fiyat (≈ 970 TL)  \n12) 12 x 32 mm priz kolye – ana PE32 hattan her rotor için branşman çıkışı – Yaklaşık fiyat (12 × 38 TL ≈ 460 TL)  \n13) 24 x 20 × 1/2\" kaplin dış dişli dirsek – priz kolyeden PE20’ye ve rotorlara dönüşlü bağlantı – Yaklaşık fiyat (24 × 18,5 TL ≈ 445 TL)  \n14) 20 x PE kaplin/dirsek/TE (20 ve 32 mm karışık) – hat dönüşleri, ekler ve dağıtım noktaları – Yaklaşık fiyat (≈ 600 TL)  \n15) 1 x Sulama sinyal kablosu 7 damarlı (SSK7, 50 m) – kontrol ünitesinden 4 solenoid vanaya kumanda kablosu – Yaklaşık fiyat (50 × 45,54 TL ≈ 2.275 TL)  \n16) 1 x Veron teflon bant küçük (2 rulo düşün) – tüm dişli bağlantılarda sızdırmazlık için – Yaklaşık fiyat (≈ 28 TL)  \n17) 20 x Damlama kazığı / gözlük tapa / küçük damla fittings karışık – damla hatlarını sabitleme ve uç kapama – Yaklaşık fiyat (≈ 150 TL)  \n18) 1 x Klasik boru kesme makası 16–42 mm – PE ve damla borularını düzgün kesmek için – Yaklaşık fiyat (≈ 580 TL)  \n\nToplam yaklaşık: 22.000–26.000 TL (malzeme, işçilik hariç)."
      }
    ],
    "projects": [],
    "createdAt": "2025-12-08T20:43:09.733Z"
  }
]